Workbook

Sheet Data Sources
A1: ID | B1: Cadence | C1: Batch Job | D1: Run Time (ET) | E1: Run Time (PT) | F1: Calls / Run | G1: Runs / Month | H1: Calls / Month | I1: Priority | J1: Current Cost ($/mo) | K1: Paid Plan (if needed) | L1: Paid Plan Cost ($/mo) | M1: Likelihood of Paying | N1: Likelihood Band | O1: Expected Cost ($/mo) | P1: Cost Trigger | Q1: Category | R1: Data Item | S1: Source | T1: Access Type | U1: Endpoint / URL | V1: Example Params / Notes on Call | W1: Auth | X1: Cost / Limits | Y1: Format | Z1: Role | AA1: Notes | AB1: Schedule Note | AC1: Holiday Calendar
A2: DS-02 | B2: Hourly | C2: H1 | D2: Hourly at :05, 10:05–16:05 (early-close days: 10:05–13:05) | E2: Hourly at :05, 07:05–13:05 (early-close days: 07:05–10:05) | F2: 1 | G2: 145.91667 | H2: =F2*G2 -> 145.91667 | I2: P1 | J2: 0 | K2: Not used – free tier only ($0 data budget) | L2: 0 | M2: 0 | N2: =IF(L2=0,"None",IF(M2>0.6,"High",IF(M2>0.2,"Medium","Low"))) -> None | O2: =J2+(L2-J2)*M2 -> 0 | P2: Use free IEX feed; full-market volume not required for hourly trend | Q2: Stock price | R2: Hourly bars: TSLA, SPCX + index/sector ETF proxies (SPY, DIA, QQQ, IWM, XLY, ITA, SMH) + any user-added tickers (primary) | S2: Alpaca Market Data | T2: REST | U2: https://data.alpaca.markets/v2/stocks/bars?symbols=TSLA,SPCX,SPY,DIA,QQQ,IWM,XLY,ITA,SMH&timeframe=1Hour&feed=iex | V2: Both tickers in one call; snapshots: /v2/stocks/snapshots?symbols=TSLA,SPCX | W2: API key + secret (free account) | X2: Free Basic plan (IEX feed, 200 calls/min) | Y2: JSON | Z2: Primary | AA2: FREE-TIER IMPACT: now the primary price source; ETF proxies ride in the same call (still 1 call/run). Prices match the consolidated tape closely; volume is IEX-only (a small share of total volume), so volume charts show trend, not true totals. No real-time SIP feed. | AB2: Primary: one multi-symbol call returns hourly bars for TSLA, SPCX and the 7 ETF proxies (union of all users' tickers) | AC2: US-MKT (NYSE trading days)
A3: DS-35 | B3: Hourly | C3: H2 | D3: Hourly at :15, 24 runs | E3: Hourly at :15, 24 runs | F3: 1 | G3: 502 | H3: =F3*G3 -> 502 | I3: P2 | J3: 0 | K3: Free – no paid plan needed | L3: 0 | M3: 0 | N3: =IF(L3=0,"None",IF(M3>0.6,"High",IF(M3>0.2,"Medium","Low"))) -> None | O3: =J3+(L3-J3)*M3 -> 0 | Q3: Geopolitical | R3: Global news events, tone, themes | S3: GDELT DOC 2.0 API | T3: REST | U3: https://api.gdeltproject.org/api/v2/doc/doc?query=(tariff OR sanctions OR Taiwan) sourcelang:english&mode=artlist&format=json&timespan=1h | V3: mode=timelinetone for sentiment trend | W3: None | X3: Free | Y3: JSON | Z3: Primary | AA3: Updates every 15 min; noisy, needs filtering | AB3: One combined query (tariff OR sanctions OR Taiwan OR ...) | AC3: US-MKT (NYSE trading days)
A4: DS-40 | B4: Hourly | C4: H2 | D4: Hourly at :15, 06:15–21:15 only (16 runs) | E4: Hourly at :15, 03:15–18:15 only (16 runs) | F4: 1 | G4: 334.66667 | H4: =F4*G4 -> 334.66667 | I4: P2 | J4: 0 | K4: Not used – free tier only ($0 data budget) | L4: 0 | M4: 0 | N4: =IF(L4=0,"None",IF(M4>0.6,"High",IF(M4>0.2,"Medium","Low"))) -> None | O4: =J4+(L4-J4)*M4 -> 0 | P4: Stay on free 25 calls/day: news polling capped at 16 calls/day | Q4: Financial news | R4: Ticker news + sentiment (union of all users' tickers, rotated) | S4: Alpha Vantage NEWS_SENTIMENT | T4: REST | U4: https://www.alphavantage.co/query?function=NEWS_SENTIMENT&tickers={TICKER}&apikey={KEY} | V4: One ticker per call (multiple tickers narrow results to articles mentioning all of them); rotation e.g. TSLA, SPCX, TSLA, SPCX… then user-added tickers | W4: API key | X4: Free 25 calls/day (capped at 16/day by schedule) | Y4: JSON | Z4: Primary | AA4: FREE-TIER IMPACT: capped at 16 calls/day (06:15–21:15 ET) to stay under the free 25/day. Collectors read the union of all users' tickers but sentiment rotates one ticker per call (fixed list or rotation), so each ticker refreshes every few hours, not hourly; no overnight updates. | AB4: One ticker per run from a fixed rotation over the union of users' tickers; hard cap 16/day (free limit 25) | AC4: US-MKT (NYSE trading days)
A5: DS-41 | B5: Hourly | C5: H2 | D5: Hourly at :15, 24 runs | E5: Hourly at :15, 24 runs | F5: 2 | G5: 502 | H5: =F5*G5 -> 1004 | I5: P1 | J5: 0 | K5: Free – no paid plan needed | L5: 0 | M5: 0 | N5: =IF(L5=0,"None",IF(M5>0.6,"High",IF(M5>0.2,"Medium","Low"))) -> None | O5: =J5+(L5-J5)*M5 -> 0 | Q5: Financial news | R5: Company news | S5: Finnhub | T5: REST | U5: https://finnhub.io/api/v1/company-news?symbol=TSLA&from={d}&to={d}&token={KEY} | V5: General: /news?category=general | W5: API key | X5: Free | Y5: JSON | Z5: Primary | AB5: TSLA + SPCX; also covers DS-78 | AC5: US-MKT (NYSE trading days)
A6: DS-44 | B6: Hourly | C6: H2 | D6: Hourly at :15, 24 runs | E6: Hourly at :15, 24 runs | F6: 3 | G6: 502 | H6: =F6*G6 -> 1506 | I6: P2 | J6: 0 | K6: Free – no paid plan needed | L6: 0 | M6: 0 | N6: =IF(L6=0,"None",IF(M6>0.6,"High",IF(M6>0.2,"Medium","Low"))) -> None | O6: =J6+(L6-J6)*M6 -> 0 | Q6: Financial news | R6: Headline RSS | S6: Google News RSS | T6: RSS | U6: https://news.google.com/rss/search?q=Tesla+stock&hl=en-US&gl=US&ceid=US:en | V6: Separate feeds for SpaceX, Fed, tariffs | W6: None | X6: Free | Y6: RSS XML | Z6: Fallback | AA6: No sentiment; aggregator links | AB6: 3 queries: Tesla, SpaceX/Starlink/Starship, Robotaxi/Cybercab; also covers DS-79 | AC6: US-MKT (NYSE trading days)
A7: DS-77 | B7: Hourly | C7: H2 | D7: Hourly at :15, 24 runs | E7: Hourly at :15, 24 runs | F7: 1 | G7: 502 | H7: =F7*G7 -> 502 | I7: P2 | J7: 0 | K7: Free – no paid plan needed | L7: 0 | M7: 0 | N7: =IF(L7=0,"None",IF(M7>0.6,"High",IF(M7>0.2,"Medium","Low"))) -> None | O7: =J7+(L7-J7)*M7 -> 0 | Q7: SpaceX news | R7: Space-industry articles & reports linked to launches | S7: Spaceflight News API (SNAPI) v4 | T7: REST | U7: https://api.spaceflightnewsapi.net/v4/articles/?search=SpaceX&ordering=-published_at | V7: Also /v4/reports/, /v4/blogs/; filter launch=<LL2 launch id> | W7: None | X7: Free | Y7: JSON | Z7: Primary | AA7: Same org as Launch Library 2, IDs link across | AC7: US-MKT (NYSE trading days)
A8: DS-06 | B8: Hourly | C8: H3 | D8: Hourly at :25, 06:25–22:25 | E8: Hourly at :25, 03:25–19:25 | F8: 1 | G8: 354.16667 | H8: =F8*G8 -> 354.16667 | I8: P1 | J8: 0 | K8: Free – no paid plan needed | L8: 0 | M8: 0 | N8: =IF(L8=0,"None",IF(M8>0.6,"High",IF(M8>0.2,"Medium","Low"))) -> None | O8: =J8+(L8-J8)*M8 -> 0 | Q8: SpaceX valuation / listing | R8: SPCX listing details, share count, lock-up, filings | S8: SEC EDGAR (company_tickers + submissions) | T8: REST | U8: https://www.sec.gov/files/company_tickers.json -> https://data.sec.gov/submissions/CIK{10-digit CIK}.json | V8: Resolve SPCX CIK from company_tickers.json; S-1/424B4 prospectus, Form 4 insider trades, 13D/G | W8: None (User-Agent header with email required) | X8: Free | Y8: JSON | Z8: Primary | AA8: SpaceX listed on Nasdaq as SPCX on 12 Jun 2026; track lock-up expiry dates from prospectus | AB8: One EDGAR submissions call for SPCX catches new 8-K, Form 4, 10-Q | AC8: US-FED (US federal business days)
A9: DS-08 | B9: Hourly | C9: H3 | D9: Hourly at :25, 06:25–22:25 | E9: Hourly at :25, 03:25–19:25 | F9: 1 | G9: 354.16667 | H9: =F9*G9 -> 354.16667 | I9: P2 | J9: 0 | K9: Not used – free tier only ($0 data budget) | L9: 0 | M9: 0 | N9: =IF(L9=0,"None",IF(M9>0.6,"High",IF(M9>0.2,"Medium","Low"))) -> None | O9: =J9+(L9-J9)*M9 -> 0 | P9: Free 15 calls/hour; we use 1/hour | Q9: SpaceX operations | R9: Launch schedule & outcomes (Starship, Falcon, Starlink) | S9: The Space Devs – Launch Library 2 | T9: REST | U9: https://ll.thespacedevs.com/2.3.0/launches/upcoming/?lsp__name=SpaceX | V9: Also /launches/previous/; dev mirror lldev.thespacedevs.com for testing | W9: None (key for higher limits) | X9: Free 15 req/hr; Patreon tiers | Y9: JSON | Z9: Primary | AA9: FREE-TIER IMPACT: none – free 15 calls/hour; schedule uses 1/hour. | AB9: One call returns all upcoming SpaceX launches | AC9: US-FED (US federal business days)
A10: DS-09 | B10: Hourly | C10: H3 | D10: Hourly at :25, 06:25–22:25 | E10: Hourly at :25, 03:25–19:25 | F10: 1 | G10: 354.16667 | H10: =F10*G10 -> 354.16667 | I10: P3 | J10: 0 | K10: Free – no paid plan needed | L10: 0 | M10: 0 | N10: =IF(L10=0,"None",IF(M10>0.6,"High",IF(M10>0.2,"Medium","Low"))) -> None | O10: =J10+(L10-J10)*M10 -> 0 | Q10: SpaceX operations | R10: Company updates | S10: SpaceX website | T10: Web | U10: https://www.spacex.com/updates/ | V10: Scrape/monitor for new posts | W10: None | X10: Free | Y10: HTML | Z10: Secondary | AC10: US-FED (US federal business days)
A11: DS-10 | B11: Hourly | C11: H3 | D11: Hourly at :25, 06:25–22:25 | E11: Hourly at :25, 03:25–19:25 | F11: 1 | G11: 354.16667 | H11: =F11*G11 -> 354.16667 | I11: P1 | J11: 0 | K11: Free – no paid plan needed | L11: 0 | M11: 0 | N11: =IF(L11=0,"None",IF(M11>0.6,"High",IF(M11>0.2,"Medium","Low"))) -> None | O11: =J11+(L11-J11)*M11 -> 0 | Q11: Tesla fundamentals | R11: Filings: 10-Q, 10-K, 8-K, Form 4 | S11: SEC EDGAR | T11: REST + Atom | U11: https://data.sec.gov/submissions/CIK0001318605.json | V11: Atom: https://www.sec.gov/cgi-bin/browse-edgar?action=getcompany&CIK=0001318605&type=8-K&output=atom | W11: None (User-Agent header required) | X11: Free | Y11: JSON / Atom XML | Z11: Primary | AA11: Tesla CIK = 0001318605 | AB11: One EDGAR submissions call for TSLA | AC11: US-FED (US federal business days)
A12: DS-18 | B12: Hourly | C12: H3 | D12: Hourly at :25, 06:25–22:25 | E12: Hourly at :25, 03:25–19:25 | F12: 1 | G12: 354.16667 | H12: =F12*G12 -> 354.16667 | I12: P1 | J12: 0 | K12: Free – no paid plan needed | L12: 0 | M12: 0 | N12: =IF(L12=0,"None",IF(M12>0.6,"High",IF(M12>0.2,"Medium","Low"))) -> None | O12: =J12+(L12-J12)*M12 -> 0 | Q12: Interest rates | R12: FOMC statements, minutes, press releases | S12: Federal Reserve | T12: RSS | U12: https://www.federalreserve.gov/feeds/press_monetary.xml | V12: All releases: /feeds/press_all.xml; Speeches: /feeds/speeches.xml | W12: None | X12: Free | Y12: RSS XML | Z12: Primary | AA12: Decision released 2:00pm ET on meeting day | AB12: Plus one extra run at 14:05 ET on FOMC decision days | AC12: US-FED (US federal business days)
A13: DS-27 | B13: Hourly | C13: H3 | D13: Hourly at :25, 06:25–22:25 | E13: Hourly at :25, 03:25–19:25 | F13: 1 | G13: 354.16667 | H13: =F13*G13 -> 354.16667 | I13: P1 | J13: 0 | K13: Free – no paid plan needed | L13: 0 | M13: 0 | N13: =IF(L13=0,"None",IF(M13>0.6,"High",IF(M13>0.2,"Medium","Low"))) -> None | O13: =J13+(L13-J13)*M13 -> 0 | Q13: Tariffs | R13: Tariff rules, Section 301/232 notices, exclusions | S13: Federal Register API | T13: REST | U13: https://www.federalregister.gov/api/v1/documents.json?conditions[term]=tariff&conditions[agencies][]=trade-representative-office-of-united-states&order=newest | V13: Also agencies: international-trade-administration, industry-and-security-bureau, customs-and-border-protection | W13: None | X13: Free | Y13: JSON | Z13: Primary | AA13: Most structured source for legal tariff actions | AB13: One query combines tariff terms + USTR/ITA/BIS/CBP agencies; also covers DS-49 | AC13: US-FED (US federal business days)
A14: DS-28 | B14: Hourly | C14: H3 | D14: Hourly at :25, 06:25–22:25 | E14: Hourly at :25, 03:25–19:25 | F14: 1 | G14: 354.16667 | H14: =F14*G14 -> 354.16667 | I14: P1 | J14: 0 | K14: Free – no paid plan needed | L14: 0 | M14: 0 | N14: =IF(L14=0,"None",IF(M14>0.6,"High",IF(M14>0.2,"Medium","Low"))) -> None | O14: =J14+(L14-J14)*M14 -> 0 | Q14: Tariffs | R14: Presidential tariff proclamations & executive orders | S14: White House | T14: Web | U14: https://www.whitehouse.gov/presidential-actions/ | V14: Monitor for 'tariff', 'Section 232', 'IEEPA' | W14: None | X14: Free | Y14: HTML | Z14: Primary | AA14: Often appears before Federal Register publication | AC14: US-FED (US federal business days)
A15: DS-29 | B15: Hourly | C15: H3 | D15: Hourly at :25, 06:25–22:25 | E15: Hourly at :25, 03:25–19:25 | F15: 1 | G15: 354.16667 | H15: =F15*G15 -> 354.16667 | I15: P1 | J15: 0 | K15: Free – no paid plan needed | L15: 0 | M15: 0 | N15: =IF(L15=0,"None",IF(M15>0.6,"High",IF(M15>0.2,"Medium","Low"))) -> None | O15: =J15+(L15-J15)*M15 -> 0 | Q15: Tariffs | R15: USTR press releases (trade deals, Section 301) | S15: USTR | T15: Web | U15: https://ustr.gov/about-us/policy-offices/press-office/press-releases | W15: None | X15: Free | Y15: HTML | Z15: Primary | AC15: US-FED (US federal business days)
A16: DS-72 | B16: Hourly | C16: H3 | D16: Hourly at :25, 06:25–22:25 | E16: Hourly at :25, 03:25–19:25 | F16: 1 | G16: 354.16667 | H16: =F16*G16 -> 354.16667 | I16: P1 | J16: 0 | K16: Free – no paid plan needed | L16: 0 | M16: 0 | N16: =IF(L16=0,"None",IF(M16>0.6,"High",IF(M16>0.2,"Medium","Low"))) -> None | O16: =J16+(L16-J16)*M16 -> 0 | Q16: SpaceX contracts | R16: NASA contract awards (Artemis HLS, Crew/Cargo, launch services) | S16: NASA News Releases | T16: RSS | U16: https://www.nasa.gov/news-release/feed/ | V16: Filter titles for 'contract', 'SpaceX', 'award' | W16: None | X16: Free | Y16: RSS XML | Z16: Primary | AC16: US-FED (US federal business days)
A17: DS-13 | B17: Daily | C17: D1 | D17: 07:00 | E17: 04:00 | F17: 2 | G17: 20.833333 | H17: =F17*G17 -> 41.666667 | I17: P2 | J17: 0 | K17: Free – no paid plan needed | L17: 0 | M17: 0 | N17: =IF(L17=0,"None",IF(M17>0.6,"High",IF(M17>0.2,"Medium","Low"))) -> None | O17: =J17+(L17-J17)*M17 -> 0 | Q17: Earnings calendar | R17: TSLA & SPCX earnings dates, EPS estimates | S17: Finnhub | T17: REST | U17: https://finnhub.io/api/v1/calendar/earnings?symbol=TSLA&from={d}&to={d}&token={KEY} | W17: API key | X17: Free | Y17: JSON | Z17: Primary | AA17: Alt: Alpha Vantage function=EARNINGS_CALENDAR | AB17: TSLA + SPCX | AC17: US-MKT (NYSE trading days)
A18: DS-15 | B18: Daily | C18: D1 | D18: 07:00 | E18: 04:00 | F18: 6 | G18: 20.833333 | H18: =F18*G18 -> 125 | I18: P1 | J18: 0 | K18: Free – no paid plan needed | L18: 0 | M18: 0 | N18: =IF(L18=0,"None",IF(M18>0.6,"High",IF(M18>0.2,"Medium","Low"))) -> None | O18: =J18+(L18-J18)*M18 -> 0 | Q18: Bond yields | R18: 2Y, 10Y, 30Y yields; 10Y–2Y spread; real yields | S18: FRED (St. Louis Fed) | T18: REST | U18: https://api.stlouisfed.org/fred/series/observations?series_id=DGS10&api_key={KEY}&file_type=json | V18: series_id = DGS2, DGS10, DGS30, T10Y2Y, DFII10 (see Series IDs tab) | W18: API key (free) | X18: Free | Y18: JSON | Z18: Primary | AA18: Simplest single API for all macro series | AB18: DGS2, DGS10, DGS30, T10Y2Y, DFII10, T10YIE | AC18: US-FED (US federal business days)
A19: DS-16 | B19: Daily | C19: D1 | D19: 07:00 | E19: 04:00 | F19: 3 | G19: 20.833333 | H19: =F19*G19 -> 62.5 | I19: P1 | J19: 0 | K19: Free – no paid plan needed | L19: 0 | M19: 0 | N19: =IF(L19=0,"None",IF(M19>0.6,"High",IF(M19>0.2,"Medium","Low"))) -> None | O19: =J19+(L19-J19)*M19 -> 0 | Q19: Interest rates | R19: Fed funds target range (upper/lower), effective rate | S19: FRED | T19: REST | U19: https://api.stlouisfed.org/fred/series/observations?series_id=DFEDTARU&api_key={KEY}&file_type=json | V19: DFEDTARU, DFEDTARL, EFFR | W19: API key | X19: Free | Y19: JSON | Z19: Primary | AB19: DFEDTARU, DFEDTARL, EFFR | AC19: US-FED (US federal business days)
A20: DS-26 | B20: Daily | C20: D1 | D20: 07:00 | E20: 04:00 | F20: 1 | G20: 20.833333 | H20: =F20*G20 -> 20.833333 | I20: P2 | J20: 0 | K20: Free – no paid plan needed | L20: 0 | M20: 0 | N20: =IF(L20=0,"None",IF(M20>0.6,"High",IF(M20>0.2,"Medium","Low"))) -> None | O20: =J20+(L20-J20)*M20 -> 0 | Q20: Economic calendar | R20: Release dates for any FRED series | S20: FRED Releases API | T20: REST | U20: https://api.stlouisfed.org/fred/releases/dates?api_key={KEY}&file_type=json&realtime_start={today} | W20: API key | X20: Free | Y20: JSON | Z20: Backup | AA20: FREE-TIER IMPACT: promoted to primary for release dates (CPI, PCE, jobs). Gives dates only – no consensus values. | AB20: Source for release-day triggers (CPI, PCE) – replaces paid calendar | AC20: US-FED (US federal business days)
A21: DS-39 | B21: Daily | C21: D1 | D21: 07:00 | E21: 04:00 | F21: 1 | G21: 20.833333 | H21: =F21*G21 -> 20.833333 | I21: P3 | J21: 0 | K21: Free – no paid plan needed | L21: 0 | M21: 0 | N21: =IF(L21=0,"None",IF(M21>0.6,"High",IF(M21>0.2,"Medium","Low"))) -> None | O21: =J21+(L21-J21)*M21 -> 0 | Q21: Geopolitical | R21: Economic Policy Uncertainty index (daily) | S21: FRED | T21: REST | U21: https://api.stlouisfed.org/fred/series/observations?series_id=USEPUINDXD&api_key={KEY}&file_type=json | W21: API key | X21: Free | Y21: JSON | Z21: Secondary | AC21: US-FED (US federal business days)
A22: DS-45 | B22: Daily | C22: D1 | D22: 07:00 | E22: 04:00 | F22: 3 | G22: 20.833333 | H22: =F22*G22 -> 62.5 | I22: P3 | J22: 0 | K22: Free – no paid plan needed | L22: 0 | M22: 0 | N22: =IF(L22=0,"None",IF(M22>0.6,"High",IF(M22>0.2,"Medium","Low"))) -> None | O22: =J22+(L22-J22)*M22 -> 0 | Q22: Market context | R22: VIX, US Dollar Index, WTI oil | S22: FRED | T22: REST | U22: https://api.stlouisfed.org/fred/series/observations?series_id=VIXCLS&api_key={KEY}&file_type=json | V22: VIXCLS, DTWEXBGS, DCOILWTICO | W22: API key | X22: Free | Y22: JSON | Z22: Optional | AA22: Risk-sentiment overlays | AB22: VIXCLS, DTWEXBGS, DCOILWTICO | AC22: US-FED (US federal business days)
A23: DS-88 | B23: Daily | C23: D1 | D23: 07:00 | E23: 04:00 | F23: 1 | G23: 20.833333 | H23: =F23*G23 -> 20.833333 | I23: P2 | J23: 0 | K23: Free – no paid plan needed | L23: 0 | M23: 0 | N23: =IF(L23=0,"None",IF(M23>0.6,"High",IF(M23>0.2,"Medium","Low"))) -> None | O23: =J23+(L23-J23)*M23 -> 0 | Q23: Interest rates | R23: Market-implied fed funds rate probabilities (replaces CME FedWatch) | S23: Atlanta Fed Market Probability Tracker | T23: Web + data download | U23: https://www.atlantafed.org/cenfis/market-probability-tracker | V23: Historical data download link on the page; RSS: https://www.atlantafed.org/RSS/MarketProbabilityTracker | W23: None | X23: Free | Y23: XLSX/CSV | Z23: Primary | AA23: Derived from CME SOFR options; updated each business day with prior-day data. Quarterly horizons, not meeting-by-meeting | AB23: Prior-day data available by morning | AC23: US-FED (US federal business days)
A24: DS-31 | B24: Daily | C24: D2 | D24: 07:30 | E24: 04:30 | F24: 1 | G24: 20.833333 | H24: =F24*G24 -> 20.833333 | I24: P2 | J24: 0 | K24: Free – no paid plan needed | L24: 0 | M24: 0 | N24: =IF(L24=0,"None",IF(M24>0.6,"High",IF(M24>0.2,"Medium","Low"))) -> None | O24: =J24+(L24-J24)*M24 -> 0 | Q24: Tariffs | R24: CBP implementation notices (CSMS) | S24: US Customs & Border Protection | T24: Web / email | U24: https://www.cbp.gov/trade/automated/cargo-systems-messaging-service | W24: None | X24: Free | Y24: HTML | Z24: Secondary | AA24: Effective-date details for collection | AC24: US-FED (US federal business days)
A25: DS-32 | B25: Daily | C25: D2 | D25: 07:30 | E25: 04:30 | F25: 1 | G25: 20.833333 | H25: =F25*G25 -> 20.833333 | I25: P2 | J25: 0 | K25: Free – no paid plan needed | L25: 0 | M25: 0 | N25: =IF(L25=0,"None",IF(M25>0.6,"High",IF(M25>0.2,"Medium","Low"))) -> None | O25: =J25+(L25-J25)*M25 -> 0 | Q25: Tariffs | R25: Export controls (chips, batteries, critical minerals) | S25: Commerce – BIS | T25: Web | U25: https://www.bis.gov/news-updates | V25: Also via Federal Register agency=industry-and-security-bureau | W25: None | X25: Free | Y25: HTML | Z25: Secondary | AC25: US-FED (US federal business days)
A26: DS-33 | B26: Daily | C26: D2 | D26: 07:30 | E26: 04:30 | F26: 1 | G26: 20.833333 | H26: =F26*G26 -> 20.833333 | I26: P3 | J26: 0 | K26: Free – no paid plan needed | L26: 0 | M26: 0 | N26: =IF(L26=0,"None",IF(M26>0.6,"High",IF(M26>0.2,"Medium","Low"))) -> None | O26: =J26+(L26-J26)*M26 -> 0 | Q26: Tariffs | R26: China counter-measures (rare earths, export bans) | S26: China MOFCOM | T26: Web | U26: http://english.mofcom.gov.cn/ | W26: None | X26: Free | Y26: HTML | Z26: Secondary | AA26: English site lags Chinese site | AC26: CN (China State Council holidays)
A27: DS-37 | B27: Daily | C27: D2 | D27: 07:30 | E27: 04:30 | F27: 1 | G27: 20.833333 | H27: =F27*G27 -> 20.833333 | I27: P2 | J27: 0 | K27: Free – no paid plan needed | L27: 0 | M27: 0 | N27: =IF(L27=0,"None",IF(M27>0.6,"High",IF(M27>0.2,"Medium","Low"))) -> None | O27: =J27+(L27-J27)*M27 -> 0 | Q27: Geopolitical | R27: US sanctions actions | S27: Treasury OFAC | T27: Web / data files | U27: https://ofac.treasury.gov/recent-actions | V27: SDN list download: https://sanctionslist.ofac.treas.gov/ | W27: None | X27: Free | Y27: HTML / XML | Z27: Primary | AC27: US-FED (US federal business days)
A28: DS-47 | B28: Daily | C28: D2 | D28: 07:30 | E28: 04:30 | F28: 1 | G28: 20.833333 | H28: =F28*G28 -> 20.833333 | I28: P1 | J28: 0 | K28: Free – no paid plan needed | L28: 0 | M28: 0 | N28: =IF(L28=0,"None",IF(M28>0.6,"High",IF(M28>0.2,"Medium","Low"))) -> None | O28: =J28+(L28-J28)*M28 -> 0 | Q28: Robotaxi – US federal | R28: Defect investigations, audit queries, special orders (e.g., Cybercab AQ26002) | S28: NHTSA Office of Defects Investigation | T28: CSV (zip) + Web | U28: https://static.nhtsa.gov/odi/ffdd/inv/FLAT_INV.zip | V28: Search UI: https://www.nhtsa.gov/recalls (make=TESLA); press: https://www.nhtsa.gov/press-releases | W28: None | X28: Free | Y28: TXT/CSV | Z28: Primary | AA28: Investigation openings/escalations are price-moving | AC28: US-FED (US federal business days)
A29: DS-48 | B29: Daily | C29: D2 | D29: 07:30 | E29: 04:30 | F29: 3 | G29: 20.833333 | H29: =F29*G29 -> 62.5 | I29: P2 | J29: 0 | K29: Free – no paid plan needed | L29: 0 | M29: 0 | N29: =IF(L29=0,"None",IF(M29>0.6,"High",IF(M29>0.2,"Medium","Low"))) -> None | O29: =J29+(L29-J29)*M29 -> 0 | Q29: Robotaxi – US federal | R29: Recalls & complaints for Tesla models | S29: NHTSA vPIC / Recalls API | T29: REST | U29: https://api.nhtsa.gov/recalls/recallsByVehicle?make=TESLA&model=MODEL%20Y&modelYear=2026 | V29: Complaints: https://api.nhtsa.gov/complaints/complaintsByVehicle?make=TESLA&model=CYBERCAB&modelYear=2026 | W29: None | X29: Free | Y29: JSON | Z29: Primary | AB29: Model Y, Model 3, Cybercab | AC29: US-FED (US federal business days)
A30: DS-60 | B30: Daily | C30: D2 | D30: 07:30 | E30: 04:30 | F30: 1 | G30: 20.833333 | H30: =F30*G30 -> 20.833333 | I30: P1 | J30: 0 | K30: Free – no paid plan needed | L30: 0 | M30: 0 | N30: =IF(L30=0,"None",IF(M30>0.6,"High",IF(M30>0.2,"Medium","Low"))) -> None | O30: =J30+(L30-J30)*M30 -> 0 | Q30: Robotaxi – company | R30: Service areas, cities, app availability | S30: Tesla Robotaxi site / X account | T30: Web | U30: https://www.tesla.com/robotaxi | V30: Also official X: @robotaxi and @Tesla_AI for area expansions | W30: None | X30: Free | Y30: HTML | Z30: Primary | AA30: Tesla doesn't publish fleet size; quarterly letters give cumulative miles | AC30: US-FED (US federal business days)
A31: DS-61 | B31: Daily | C31: D2 | D31: 07:30 | E31: 04:30 | F31: 1 | G31: 20.833333 | H31: =F31*G31 -> 20.833333 | I31: P3 | J31: 0 | K31: Free – no paid plan needed | L31: 0 | M31: 0 | N31: =IF(L31=0,"None",IF(M31>0.6,"High",IF(M31>0.2,"Medium","Low"))) -> None | O31: =J31+(L31-J31)*M31 -> 0 | Q31: Robotaxi – trackers | R31: Aggregated state permit rosters & fleet sizes (Tesla, Waymo, Zoox) | S31: Robotaxi Tracker | T31: Web | U31: https://robotaxitracker.com/permits | V31: Methodology: https://robotaxitracker.com/methodology | W31: None | X31: Free (attribution required) | Y31: HTML | Z31: Secondary | AA31: Unofficial – cross-check against TxDMV/CA DMV | AC31: US-FED (US federal business days)
A32: DS-64 | B32: Daily | C32: D2 | D32: 07:30 | E32: 04:30 | F32: 1 | G32: 20.833333 | H32: =F32*G32 -> 20.833333 | I32: P1 | J32: 0 | K32: Free – no paid plan needed | L32: 0 | M32: 0 | N32: =IF(L32=0,"None",IF(M32>0.6,"High",IF(M32>0.2,"Medium","Low"))) -> None | O32: =J32+(L32-J32)*M32 -> 0 | Q32: SpaceX launches | R32: FAA launch/reentry licenses, Starship license mods, mishap investigations | S32: FAA Office of Commercial Space Transportation | T32: Web | U32: https://www.faa.gov/space/licenses/operator_licenses_permits | V32: Data: https://www.faa.gov/data_research/commercial_space_data ; Starship: https://www.faa.gov/space/stakeholder_engagement/spacex_starship | W32: None | X32: Free | Y32: HTML | Z32: Primary | AA32: Groundings after mishaps move SPCX | AC32: US-FED (US federal business days)
A33: DS-65 | B33: Daily | C33: D2 | D33: 07:30 | E33: 04:30 | F33: 1 | G33: 20.833333 | H33: =F33*G33 -> 20.833333 | I33: P2 | J33: 0 | K33: Free – no paid plan needed | L33: 0 | M33: 0 | N33: =IF(L33=0,"None",IF(M33>0.6,"High",IF(M33>0.2,"Medium","Low"))) -> None | O33: =J33+(L33-J33)*M33 -> 0 | Q33: SpaceX launches | R33: Starlink constellation size (on-orbit satellites) | S33: CelesTrak | T33: REST | U33: https://celestrak.org/NORAD/elements/gp.php?GROUP=starlink&FORMAT=json | V33: Count objects per day for constellation growth | W33: None | X33: Free | Y33: JSON | Z33: Primary | AA33: Space-Track.org is the authoritative alt (free account) | AB33: CelesTrak asks for ≤1 download per 2 hours; daily is well within | AC33: US-FED (US federal business days)
A34: DS-71 | B34: Daily | C34: D2 | D34: 07:30 | E34: 04:30 | F34: 1 | G34: 20.833333 | H34: =F34*G34 -> 20.833333 | I34: P2 | J34: 0 | K34: Free – no paid plan needed | L34: 0 | M34: 0 | N34: =IF(L34=0,"None",IF(M34>0.6,"High",IF(M34>0.2,"Medium","Low"))) -> None | O34: =J34+(L34-J34)*M34 -> 0 | Q34: SpaceX contracts | R34: NSSL launch assignments & Space Force awards | S34: Space Systems Command | T34: Web | U34: https://www.ssc.spaceforce.mil/News | W34: None | X34: Free | Y34: HTML | Z34: Primary | AC34: US-FED (US federal business days)
A35: DS-74 | B35: Daily | C35: D2 | D35: 07:30 | E35: 04:30 | F35: 1 | G35: 20.833333 | H35: =F35*G35 -> 20.833333 | I35: P2 | J35: 0 | K35: Free – no paid plan needed | L35: 0 | M35: 0 | N35: =IF(L35=0,"None",IF(M35>0.6,"High",IF(M35>0.2,"Medium","Low"))) -> None | O35: =J35+(L35-J35)*M35 -> 0 | Q35: SpaceX customers | R35: Starlink licensing, spectrum, direct-to-cell filings | S35: FCC ECFS API + ICFS | T35: REST | U35: https://publicapi.fcc.gov/ecfs/filings?api_key={KEY}&q=SpaceX&sort=date_disseminated,DESC | V35: Satellite applications: https://licensing.fcc.gov/myibfs/ (ICFS); api.data.gov key | W35: API key (api.data.gov) | X35: Free | Y35: JSON | Z35: Primary | AA35: Spectrum approvals drive Starlink capacity | AC35: US-FED (US federal business days)
A36: DS-76 | B36: Daily | C36: D2 | D36: 07:30 | E36: 04:30 | F36: 1 | G36: 20.833333 | H36: =F36*G36 -> 20.833333 | I36: P2 | J36: 0 | K36: Free – no paid plan needed | L36: 0 | M36: 0 | N36: =IF(L36=0,"None",IF(M36>0.6,"High",IF(M36>0.2,"Medium","Low"))) -> None | O36: =J36+(L36-J36)*M36 -> 0 | Q36: SpaceX customers | R36: Commercial customer announcements (airlines, telcos, governments) | S36: Starlink updates | T36: Web | U36: https://www.starlink.com/updates | V36: Also Starlink business/aviation press pages | W36: None | X36: Free | Y36: HTML | Z36: Secondary | AC36: US-FED (US federal business days)
A37: DS-17 | B37: Daily | C37: D3 | D37: 09:15 | E37: 06:15 | F37: 2 | G37: 20.833333 | H37: =F37*G37 -> 41.666667 | I37: P2 | J37: 0 | K37: Free – no paid plan needed | L37: 0 | M37: 0 | N37: =IF(L37=0,"None",IF(M37>0.6,"High",IF(M37>0.2,"Medium","Low"))) -> None | O37: =J37+(L37-J37)*M37 -> 0 | Q37: Interest rates | R37: Effective Fed Funds Rate & SOFR | S37: NY Fed Markets API | T37: REST | U37: https://markets.newyorkfed.org/api/rates/unsecured/effr/last/1.json | V37: SOFR: /api/rates/secured/sofr/last/1.json | W37: None | X37: Free | Y37: JSON | Z37: Primary | AB37: EFFR + SOFR (published ~09:00 ET) | AC37: US-FED (US federal business days)
A38: DS-01 | B38: Daily | C38: D4 | D38: 16:45 | E38: 13:45 | F38: 9 | G38: 20.75 | H38: =F38*G38 -> 186.75 | I38: P3 | J38: 0 | K38: Not used – free tier only ($0 data budget) | L38: 0 | M38: 0 | N38: =IF(L38=0,"None",IF(M38>0.6,"High",IF(M38>0.2,"Medium","Low"))) -> None | O38: =J38+(L38-J38)*M38 -> 0 | P38: Alpaca free IEX hourly bars (DS-02) become primary; Massive free tier keeps the daily-close check | Q38: Stock price | R38: Official daily close for TSLA, SPCX + ETF proxies (verifies Alpaca) | S38: Massive (formerly Polygon.io) | T38: REST | U38: https://api.massive.com/v2/aggs/ticker/{TICKER}/prev | V38: One call per ticker after the close (9 tickers); throttle to 5 calls/min (~2 minutes per run) | W38: API key | X38: Free Basic tier (5 calls/min, end-of-day + 15-min delayed) | Y38: JSON | Z38: Backup | AA38: FREE-TIER IMPACT: demoted to backup. Free Basic gives end-of-day + 15-min delayed data at 5 calls/min – enough for a daily-close check (9 calls/day incl. ETF proxies, throttled over ~2 min) and hourly failover, not primary intraday use. Fallback for index closes: FRED (DS-91). | AB38: Free tier: daily close per ticker (TSLA, SPCX + 7 ETFs), throttled to 5/min; failover for hourly bars | AC38: US-BOND (SIFMA bond-market days)
A39: DS-14 | B39: Daily | C39: D4 | D39: 16:45 | E39: 13:45 | F39: 1 | G39: 20.75 | H39: =F39*G39 -> 20.75 | I39: P1 | J39: 0 | K39: Free – no paid plan needed | L39: 0 | M39: 0 | N39: =IF(L39=0,"None",IF(M39>0.6,"High",IF(M39>0.2,"Medium","Low"))) -> None | O39: =J39+(L39-J39)*M39 -> 0 | Q39: Bond yields | R39: Daily Treasury par yield curve (1M–30Y) | S39: US Treasury | T39: XML / CSV | U39: https://home.treasury.gov/resource-center/data-chart-center/interest-rates/pages/xml?data=daily_treasury_yield_curve&field_tdr_date_value=2026 | V39: CSV: .../daily-treasury-rates.csv/2026/all?type=daily_treasury_yield_curve | W39: None | X39: Free | Y39: XML/CSV | Z39: Primary | AA39: Authoritative source for curve | AB39: Whole yield curve in one call (published ~15:30 ET) | AC39: US-BOND (SIFMA bond-market days)
A40: DS-89 | B40: Daily | C40: D4 | D40: 16:45 | E40: 13:45 | F40: 2 | G40: 20.75 | H40: =F40*G40 -> 41.5 | I40: P2 | J40: 0 | K40: Free – no paid plan needed | L40: 0 | M40: 0 | N40: =IF(L40=0,"None",IF(M40>0.6,"High",IF(M40>0.2,"Medium","Low"))) -> None | O40: =J40+(L40-J40)*M40 -> 0 | Q40: Interest rates / Inflation | R40: Meeting-level Fed decision odds and CPI outcome odds | S40: Kalshi public market data API | T40: REST | U40: https://api.elections.kalshi.com/trade-api/v2/markets?series_ticker={SERIES}&status=open | V40: Find series via /trade-api/v2/series (e.g., Fed decision and CPI series); market data needs no login | W40: None for market data | X40: Free (~20 req/s) | Y40: JSON | Z40: Secondary | AA40: Prediction-market prices; thin markets can be noisy. Read-only use, no account needed | AB40: Fed decision series + CPI series | AC40: US-MKT (NYSE trading days)
A41: DS-90 | B41: Daily | C41: D4 | D41: 16:45 | E41: 13:45 | F41: 1 | G41: 20.75 | H41: =F41*G41 -> 20.75 | I41: P1 | J41: 0 | K41: Free – no paid plan needed | L41: 0 | M41: 0 | N41: =IF(L41=0,"None",IF(M41>0.6,"High",IF(M41>0.2,"Medium","Low"))) -> None | O41: =J41+(L41-J41)*M41 -> 0 | Q41: Inflation | R41: CPI, core CPI, PCE & core PCE nowcasts (free stand-in for consensus forecasts) | S41: Cleveland Fed Inflation Nowcasting | T41: Web | U41: https://www.clevelandfed.org/indicators-and-data/inflation-nowcasting | V41: Month-over-month and year-over-year nowcasts; updated each business day ~10:00 ET | W41: None | X41: Free | Y41: HTML/JSON (page data) | Z41: Primary | AA41: CPI surprise = actual (BLS) − Cleveland Fed nowcast on the day before release | AB41: Captures the latest nowcast (updated ~10:00 ET) | AC41: US-FED (US federal business days)
A42: DS-93 | B42: Daily | C42: D4 | D42: 16:45 | E42: 13:45 | F42: 2 | G42: 20.75 | H42: =F42*G42 -> 41.5 | I42: P2 | J42: 0 | K42: Free – no paid plan needed | L42: 0 | M42: 0 | N42: =IF(L42=0,"None",IF(M42>0.6,"High",IF(M42>0.2,"Medium","Low"))) -> None | O42: =J42+(L42-J42)*M42 -> 0 | Q42: Options sentiment | R42: Put/call ratio (volume & open interest) and IV30 for TSLA, SPCX | S42: Alpaca options market data – indicative feed | T42: REST | U42: https://data.alpaca.markets/v1beta1/options/snapshots/{UNDERLYING}?feed=indicative | V42: One chain snapshot per underlying after the close; IV30 = interpolate implied vol of contracts ~30 days to expiry; P/C = put ÷ call daily volume | W42: API key + secret (free account) | X42: Free Basic plan: indicative feed (15-min delayed) – CONFIRM free tier includes chain snapshots with IV/greeks | Y42: JSON | Z42: Secondary | AA42: Confirm free tier includes it before building; if greeks/IV are missing, compute IV from option mid prices (Black-Scholes) or drop IV30 | AB42: One chain snapshot per underlying (TSLA, SPCX) | AC42: US-MKT (NYSE trading days)
A43: DS-67 | B43: Daily | C43: D5 | D43: 17:45 | E43: 14:45 | F43: 1 | G43: 20.833333 | H43: =F43*G43 -> 20.833333 | I43: P1 | J43: 0 | K43: Free – no paid plan needed | L43: 0 | M43: 0 | N43: =IF(L43=0,"None",IF(M43>0.6,"High",IF(M43>0.2,"Medium","Low"))) -> None | O43: =J43+(L43-J43)*M43 -> 0 | Q43: SpaceX contracts | R43: All federal awards to SpaceX (NASA, Space Force, NRO, etc.) | S43: USAspending.gov API | T43: REST (POST) | U43: https://api.usaspending.gov/api/v2/search/spending_by_award/ | V43: Body filters: recipient_search_text=["Space Exploration Technologies"], award_type_codes=[A,B,C,D], time_period; Tx detail: /api/v2/awards/{id}/ | W43: None | X43: Free | Y43: JSON | Z43: Primary | AA43: Includes modifications (obligation changes) | AC43: US-FED (US federal business days)
A44: DS-68 | B44: Daily | C44: D5 | D44: 17:45 | E44: 14:45 | F44: 1 | G44: 20.833333 | H44: =F44*G44 -> 20.833333 | I44: P2 | J44: 0 | K44: Free – no paid plan needed | L44: 0 | M44: 0 | N44: =IF(L44=0,"None",IF(M44>0.6,"High",IF(M44>0.2,"Medium","Low"))) -> None | O44: =J44+(L44-J44)*M44 -> 0 | Q44: SpaceX contracts | R44: Contract award records (replaces FPDS, retired Feb 2026) | S44: SAM.gov Contract Awards API | T44: REST | U44: https://api.sam.gov/contract-awards/v1/search?api_key={KEY}&awardeeLegalBusinessName=SPACE EXPLORATION TECHNOLOGIES CORP | V44: contractingDepartmentCode=8000 (NASA), 9700 (DoD); lastModifiedDate range | W44: API key (SAM.gov / Login.gov) | X44: Free; 10 req/day without role, 1,000 with role | Y44: JSON | Z44: Primary | AA44: Get a system account for 1,000+/day | AB44: Fits 10/day limit of a basic SAM.gov key | AC44: US-FED (US federal business days)
A45: DS-69 | B45: Daily | C45: D5 | D45: 17:45 | E45: 14:45 | F45: 1 | G45: 20.833333 | H45: =F45*G45 -> 20.833333 | I45: P3 | J45: 0 | K45: Free – no paid plan needed | L45: 0 | M45: 0 | N45: =IF(L45=0,"None",IF(M45>0.6,"High",IF(M45>0.2,"Medium","Low"))) -> None | O45: =J45+(L45-J45)*M45 -> 0 | Q45: SpaceX contracts | R45: Upcoming solicitations SpaceX may win (lunar, NSSL, Golden Dome) | S45: SAM.gov Contract Opportunities API | T45: REST | U45: https://api.sam.gov/opportunities/v2/search?api_key={KEY}&postedFrom={MM/dd/yyyy}&postedTo={MM/dd/yyyy}&organizationName=NATIONAL AERONAUTICS AND SPACE ADMINISTRATION | V45: Filter NAICS 336414, 336415, 481212, 517410 | W45: API key | X45: Free | Y45: JSON | Z45: Secondary | AA45: Pipeline view, not wins | AC45: US-FED (US federal business days)
A46: DS-70 | B46: Daily | C46: D5 | D46: 17:45 | E46: 14:45 | F46: 1 | G46: 20.833333 | H46: =F46*G46 -> 20.833333 | I46: P1 | J46: 0 | K46: Free – no paid plan needed | L46: 0 | M46: 0 | N46: =IF(L46=0,"None",IF(M46>0.6,"High",IF(M46>0.2,"Medium","Low"))) -> None | O46: =J46+(L46-J46)*M46 -> 0 | Q46: SpaceX contracts | R46: Daily DoD contract announcements ≥$7.5M (Space Force, NRO launches) | S46: Department of Defense – Contracts | T46: Web / RSS | U46: https://www.defense.gov/News/Contracts/ | V46: Published ~5pm ET weekdays; parse for 'Space Exploration Technologies' | W46: None | X46: Free | Y46: HTML/RSS | Z46: Primary | AB46: Announcements post ~17:00 ET | AC46: US-FED (US federal business days)
A47: DS-30 | B47: Weekly | C47: W1 | D47: Mon 08:00 | E47: Mon 05:00 | F47: 1 | G47: 4.33 | H47: =F47*G47 -> 4.33 | I47: P2 | J47: 0 | K47: Free – no paid plan needed | L47: 0 | M47: 0 | N47: =IF(L47=0,"None",IF(M47>0.6,"High",IF(M47>0.2,"Medium","Low"))) -> None | O47: =J47+(L47-J47)*M47 -> 0 | Q47: Tariffs | R47: Current tariff rates by HTS code (autos 8703, batteries 8507) | S47: USITC HTS REST API | T47: REST | U47: https://hts.usitc.gov/reststop/search?keyword=8703 | V47: Also /reststop/exportList for full schedule | W47: None | X47: Free | Y47: JSON | Z47: Primary | AA47: Reference table for affected product codes | AC47: US-FED (US federal business days)
A48: DS-36 | B48: Weekly | C48: W1 | D48: Mon 08:00 | E48: Mon 05:00 | F48: 1 | G48: 4.33 | H48: =F48*G48 -> 4.33 | I48: P3 | J48: 0 | K48: Not used – free tier only ($0 data budget) | L48: 0 | M48: 0 | N48: =IF(L48=0,"None",IF(M48>0.6,"High",IF(M48>0.2,"Medium","Low"))) -> None | O48: =J48+(L48-J48)*M48 -> 0 | P48: Open tier (aggregated data) + GDELT events (DS-35) | Q48: Geopolitical | R48: Conflict & protest events (geo-coded) | S48: ACLED API | T48: REST (OAuth) | U48: https://acleddata.com/api/acled/read?_format=json&event_date={d} | V48: Token: POST https://acleddata.com/oauth/token (myACLED account) | W48: OAuth (myACLED account) | X48: Free for non-commercial / research tier | Y48: JSON | Z48: Secondary | AA48: FREE-TIER IMPACT: personal email gets the Open tier (aggregated data only, no event-level API). Conflict events come mainly from GDELT (DS-35). | AC48: US-FED (US federal business days)
A49: DS-38 | B49: Weekly | C49: W1 | D49: Mon 08:00 | E49: Mon 05:00 | F49: 1 | G49: 4.33 | H49: =F49*G49 -> 4.33 | I49: P2 | J49: 0 | K49: Free – no paid plan needed | L49: 0 | M49: 0 | N49: =IF(L49=0,"None",IF(M49>0.6,"High",IF(M49>0.2,"Medium","Low"))) -> None | O49: =J49+(L49-J49)*M49 -> 0 | Q49: Geopolitical | R49: Geopolitical Risk (GPR) Index | S49: Caldara & Iacoviello (Fed Board) | T49: Download | U49: https://www.matteoiacoviello.com/gpr.htm | V49: Daily & monthly XLS files | W49: None | X49: Free | Y49: XLS | Z49: Primary | AA49: Single numeric risk gauge for charts | AC49: US-FED (US federal business days)
A50: DS-50 | B50: Weekly | C50: W1 | D50: Mon 08:00 | E50: Mon 05:00 | F50: 1 | G50: 4.33 | H50: =F50*G50 -> 4.33 | I50: P1 | J50: 0 | K50: Free – no paid plan needed | L50: 0 | M50: 0 | N50: =IF(L50=0,"None",IF(M50>0.6,"High",IF(M50>0.2,"Medium","Low"))) -> None | O50: =J50+(L50-J50)*M50 -> 0 | Q50: Robotaxi – California | R50: AV testing / driverless / deployment permit holders | S50: California DMV | T50: Web | U50: https://www.dmv.ca.gov/portal/vehicle-industry-services/autonomous-vehicles/autonomous-vehicle-testing-permit-holders/ | V50: Watch for Tesla moving from 'testing with driver' to driverless or deployment permit | W50: None | X50: Free | Y50: HTML | Z50: Primary | AA50: Tesla currently holds testing-with-driver permit only | AC50: US-FED (US federal business days)
A51: DS-51 | B51: Weekly | C51: W1 | D51: Mon 08:00 | E51: Mon 05:00 | F51: 1 | G51: 4.33 | H51: =F51*G51 -> 4.33 | I51: P2 | J51: 0 | K51: Free – no paid plan needed | L51: 0 | M51: 0 | N51: =IF(L51=0,"None",IF(M51>0.6,"High",IF(M51>0.2,"Medium","Low"))) -> None | O51: =J51+(L51-J51)*M51 -> 0 | Q51: Robotaxi – California | R51: AV collision reports (OL 316) | S51: California DMV | T51: Web (PDF per report) | U51: https://www.dmv.ca.gov/portal/vehicle-industry-services/autonomous-vehicles/autonomous-vehicle-collision-reports/ | V51: Structured mirror: https://tims.berkeley.edu/tools/avsafety.php | W51: None | X51: Free | Y51: PDF/HTML | Z51: Primary | AC51: US-FED (US federal business days)
A52: DS-54 | B52: Weekly | C52: W1 | D52: Mon 08:00 | E52: Mon 05:00 | F52: 1 | G52: 4.33 | H52: =F52*G52 -> 4.33 | I52: P1 | J52: 0 | K52: Free – no paid plan needed | L52: 0 | M52: 0 | N52: =IF(L52=0,"None",IF(M52>0.6,"High",IF(M52>0.2,"Medium","Low"))) -> None | O52: =J52+(L52-J52)*M52 -> 0 | Q52: Robotaxi – Texas | R52: Commercial AV authorizations & AV-registered vehicles (fleet count by model) | S52: Texas DMV – Automated Motor Vehicles Program | T52: Web | U52: https://www.txdmv.gov/AVprogram | V52: Authorization enforceable since 28 May 2026; vehicle verification portal linked from page | W52: None | X52: Free | Y52: HTML | Z52: Primary | AA52: Best official proxy for Austin/Dallas/Houston fleet size (476 Tesla vehicles as of 21 Sep 2026) | AC52: US-FED (US federal business days)
A53: DS-55 | B53: Weekly | C53: W1 | D53: Mon 08:00 | E53: Mon 05:00 | F53: 1 | G53: 4.33 | H53: =F53*G53 -> 4.33 | I53: P1 | J53: 0 | K53: Free – no paid plan needed | L53: 0 | M53: 0 | N53: =IF(L53=0,"None",IF(M53>0.6,"High",IF(M53>0.2,"Medium","Low"))) -> None | O53: =J53+(L53-J53)*M53 -> 0 | Q53: Robotaxi – Nevada | R53: Autonomous Vehicle Network Company permits (Tesla AVNC Permit 002, up to 5,000 vehicles) | S53: Nevada Transportation Authority (Dept. of Business & Industry) | T53: Web | U53: https://www.business.nv.gov/news-media/press-releases/ | V53: Also Nevada DMV AV testing licenses: https://dmv.nv.gov/autonomous.htm | W53: None | X53: Free | Y53: HTML | Z53: Primary | AA53: Approved 21 Aug 2026; Las Vegas launch pending | AC53: US-FED (US federal business days)
A54: DS-56 | B54: Weekly | C54: W1 | D54: Mon 08:00 | E54: Mon 05:00 | F54: 1 | G54: 4.33 | H54: =F54*G54 -> 4.33 | I54: P2 | J54: 0 | K54: Free – no paid plan needed | L54: 0 | M54: 0 | N54: =IF(L54=0,"None",IF(M54>0.6,"High",IF(M54>0.2,"Medium","Low"))) -> None | O54: =J54+(L54-J54)*M54 -> 0 | Q54: Robotaxi – Arizona | R54: AV self-certification & TNC (ride-hail) permits | S54: Arizona DOT (ADOT) | T54: Web | U54: https://azdot.gov/ | V54: Search ADOT site for 'autonomous vehicle'; Tesla got TNC permit Nov 2025 | W54: None | X54: Free | Y54: HTML | Z54: Secondary | AA54: Phoenix launch preparations per Q2 2026 disclosure | AC54: US-FED (US federal business days)
A55: DS-57 | B55: Weekly | C55: W1 | D55: Mon 08:00 | E55: Mon 05:00 | F55: 1 | G55: 4.33 | H55: =F55*G55 -> 4.33 | I55: P3 | J55: 0 | K55: Free – no paid plan needed | L55: 0 | M55: 0 | N55: =IF(L55=0,"None",IF(M55>0.6,"High",IF(M55>0.2,"Medium","Low"))) -> None | O55: =J55+(L55-J55)*M55 -> 0 | Q55: Robotaxi – Florida | R55: No state AV permit required; track via city/airport approvals & news | S55: Florida HSMV / local news | T55: Web | U55: https://www.flhsmv.gov/ | V55: Use news agents for Miami, Orlando, Tampa service-area changes | W55: None | X55: Free | Y55: HTML | Z55: Secondary | AA55: Fewest official data points of any operating state | AC55: US-FED (US federal business days)
A56: DS-58 | B56: Weekly | C56: W1 | D56: Mon 08:00 | E56: Mon 05:00 | F56: 1 | G56: 4.33 | H56: =F56*G56 -> 4.33 | I56: P2 | J56: 0 | K56: Free – no paid plan needed | L56: 0 | M56: 0 | N56: =IF(L56=0,"None",IF(M56>0.6,"High",IF(M56>0.2,"Medium","Low"))) -> None | O56: =J56+(L56-J56)*M56 -> 0 | Q56: Robotaxi – Europe | R56: FSD (Supervised) type approval & national recognitions | S56: RDW (Netherlands vehicle authority) | T56: Web | U56: https://www.rdw.nl/ | V56: EU harmonisation via TCMV; DCAS rule UN R171 at https://unece.org/transport/vehicle-regulations | W56: None | X56: Free | Y56: HTML | Z56: Primary | AA56: 8 countries approved as of 29 Sep 2026 (NL, BE, CZ, DK, HR, LT, SI, EE) | AC56: NL (Netherlands public holidays)
A57: DS-59 | B57: Weekly | C57: W1 | D57: Mon 08:00 | E57: Mon 05:00 | F57: 1 | G57: 4.33 | H57: =F57*G57 -> 4.33 | I57: P2 | J57: 0 | K57: Free – no paid plan needed | L57: 0 | M57: 0 | N57: =IF(L57=0,"None",IF(M57>0.6,"High",IF(M57>0.2,"Medium","Low"))) -> None | O57: =J57+(L57-J57)*M57 -> 0 | Q57: Robotaxi – China | R57: FSD / 'Tesla Assisted Driving' approval, L3/L4 pilot permits | S57: MIIT (Ministry of Industry & IT) | T57: Web | U57: https://www.miit.gov.cn/ | V57: Product announcements list; also Shanghai/Beijing robotaxi pilot zone notices | W57: None | X57: Free | Y57: HTML (Chinese) | Z57: Secondary | AA57: Supervised FSD live since 21 May 2026; full approval pending | AC57: CN (China State Council holidays)
A58: DS-62 | B58: Weekly | C58: W1 | D58: Mon 08:00 | E58: Mon 05:00 | F58: 1 | G58: 4.33 | H58: =F58*G58 -> 4.33 | I58: P3 | J58: 0 | K58: Free – no paid plan needed | L58: 0 | M58: 0 | N58: =IF(L58=0,"None",IF(M58>0.6,"High",IF(M58>0.2,"Medium","Low"))) -> None | O58: =J58+(L58-J58)*M58 -> 0 | Q58: Robotaxi – trackers | R58: Robotaxi status by city/company | S58: The Charge Port Robotaxi Tracker | T58: Web | U58: https://thechargeport.com/robotaxi-tracker | W58: None | X58: Free | Y58: HTML | Z58: Secondary | AA58: Unofficial | AC58: US-FED (US federal business days)
A59: DS-63 | B59: Weekly | C59: W1 | D59: Mon 08:00 | E59: Mon 05:00 | F59: 1 | G59: 4.33 | H59: =F59*G59 -> 4.33 | I59: P3 | J59: 0 | K59: Free – no paid plan needed | L59: 0 | M59: 0 | N59: =IF(L59=0,"None",IF(M59>0.6,"High",IF(M59>0.2,"Medium","Low"))) -> None | O59: =J59+(L59-J59)*M59 -> 0 | Q59: Robotaxi – trackers | R59: FSD approvals by country (EU) & US rollout | S59: Not a Tesla App / NotAnFSDTracker | T59: Web | U59: https://notanfsdtracker.com/eu-tracker | V59: US: https://notanfsdtracker.com/united-states-tesla-robotaxi-rollout-2026 | W59: None | X59: Free | Y59: HTML | Z59: Secondary | AA59: Unofficial | AC59: US-FED (US federal business days)
A60: DS-66 | B60: Weekly | C60: W1 | D60: Mon 08:00 | E60: Mon 05:00 | F60: 1 | G60: 4.33 | H60: =F60*G60 -> 4.33 | I60: P3 | J60: 0 | K60: Free – no paid plan needed | L60: 0 | M60: 0 | N60: =IF(L60=0,"None",IF(M60>0.6,"High",IF(M60>0.2,"Medium","Low"))) -> None | O60: =J60+(L60-J60)*M60 -> 0 | Q60: SpaceX launches | R60: Launch & Starlink statistics | S60: Jonathan McDowell – planet4589 | T60: Web | U60: https://planet4589.org/space/con/star/stats.html | W60: None | X60: Free | Y60: HTML | Z60: Secondary | AA60: Widely used independent stats | AC60: US-FED (US federal business days)
A61: DS-73 | B61: Weekly | C61: W1 | D61: Mon 08:00 | E61: Mon 05:00 | F61: 1 | G61: 4.33 | H61: =F61*G61 -> 4.33 | I61: P3 | J61: 0 | K61: Free – no paid plan needed | L61: 0 | M61: 0 | N61: =IF(L61=0,"None",IF(M61>0.6,"High",IF(M61>0.2,"Medium","Low"))) -> None | O61: =J61+(L61-J61)*M61 -> 0 | Q61: SpaceX contracts | R61: Bid protests of NASA/DoD awards (risk to wins) | S61: GAO Bid Protest Decisions | T61: Web | U61: https://www.gao.gov/legal/bid-protests/search | V61: Search 'Space Exploration Technologies' or 'SpaceX' | W61: None | X61: Free | Y61: HTML | Z61: Optional | AC61: US-FED (US federal business days)
A62: DS-80 | B62: Monthly / on release | C62: C1 | D62: 1st US federal business day of month, 06:00 | E62: 03:00 | F62: 0 | G62: 1 | H62: =F62*G62 -> 0 | I62: P1 | J62: 0 | K62: Free – no paid plan needed | L62: 0 | M62: 0 | N62: =IF(L62=0,"None",IF(M62>0.6,"High",IF(M62>0.2,"Medium","Low"))) -> None | O62: =J62+(L62-J62)*M62 -> 0 | Q62: Calendars | R62: NYSE trading sessions, holidays & 1pm early closes | S62: exchange_calendars (Python library, calendar XNYS) | T62: Library (offline) | U62: https://pypi.org/project/exchange-calendars/ | V62: xc.get_calendar('XNYS').is_session(date); session_close(date) for early closes | W62: None | X62: Free (open source) | Y62: Python | Z62: Primary | AA62: No API calls; upgrade the package yearly so new-year holidays are included | AB62: Offline library – no API calls | AC62: US-FED (US federal business days)
A63: DS-81 | B63: Monthly / on release | C63: C1 | D63: 1st US federal business day of month, 06:00 | E63: 03:00 | F63: 0 | G63: 1 | H63: =F63*G63 -> 0 | I63: P1 | J63: 0 | K63: Free – no paid plan needed | L63: 0 | M63: 0 | N63: =IF(L63=0,"None",IF(M63>0.6,"High",IF(M63>0.2,"Medium","Low"))) -> None | O63: =J63+(L63-J63)*M63 -> 0 | Q63: Calendars | R63: US federal, China (incl. make-up days) & Netherlands public holidays | S63: holidays (Python library) | T63: Library (offline) | U63: https://pypi.org/project/holidays/ | V63: holidays.US(), holidays.financial_holidays('NYSE'), holidays.CN(language='en_US'), holidays.NL() | W63: None | X63: Free (open source) | Y63: Python | Z63: Primary | AA63: China dates for next year only appear once the State Council publishes them | AB63: Offline library – no API calls | AC63: US-FED (US federal business days)
A64: DS-82 | B64: Monthly / on release | C64: C1 | D64: 1st US federal business day of month, 06:00 | E64: 03:00 | F64: 1 | G64: 1 | H64: =F64*G64 -> 1 | I64: P2 | J64: 0 | K64: Free – no paid plan needed | L64: 0 | M64: 0 | N64: =IF(L64=0,"None",IF(M64>0.6,"High",IF(M64>0.2,"Medium","Low"))) -> None | O64: =J64+(L64-J64)*M64 -> 0 | Q64: Calendars | R64: Market calendar check incl. early closes (confirms library) | S64: Alpaca Calendar API | T64: REST | U64: https://paper-api.alpaca.markets/v2/calendar?start={YYYY-MM-01}&end={YYYY-MM-last} | V64: Returns each trading date with open/close times | W64: API key + secret (free account) | X64: Free | Y64: JSON | Z64: Secondary | AA64: One call a month; alert if it disagrees with exchange_calendars | AB64: One call per month | AC64: US-FED (US federal business days)
A65: DS-19 | B65: Monthly / on release | C65: M1 | D65: 1st business day of month, 08:00 | E65: 1st business day of month, 05:00 | F65: 1 | G65: 1 | H65: =F65*G65 -> 1 | I65: P1 | J65: 0 | K65: Free – no paid plan needed | L65: 0 | M65: 0 | N65: =IF(L65=0,"None",IF(M65>0.6,"High",IF(M65>0.2,"Medium","Low"))) -> None | O65: =J65+(L65-J65)*M65 -> 0 | Q65: Interest rates | R65: FOMC meeting calendar & dot plot (SEP) | S65: Federal Reserve | T65: Web | U65: https://www.federalreserve.gov/monetarypolicy/fomccalendars.htm | V65: SEP published at Mar/Jun/Sep/Dec meetings | W65: None | X65: Free | Y65: HTML | Z65: Primary | AA65: 8 scheduled meetings/year | AB65: Calendar + SEP check | AC65: Release calendar
A66: DS-21 | B66: Monthly / on release | C66: M1 | D66: 08:35 on BLS CPI release day | E66: 05:35 on BLS CPI release day | F66: 1 | G66: 1 | H66: =F66*G66 -> 1 | I66: P1 | J66: 0 | K66: Free – no paid plan needed | L66: 0 | M66: 0 | N66: =IF(L66=0,"None",IF(M66>0.6,"High",IF(M66>0.2,"Medium","Low"))) -> None | O66: =J66+(L66-J66)*M66 -> 0 | Q66: Inflation | R66: CPI-U headline & core (SA/NSA) | S66: BLS Public Data API v2 | T66: REST (POST) | U66: https://api.bls.gov/publicAPI/v2/timeseries/data/ | V66: Body: {"seriesid":["CUSR0000SA0","CUSR0000SA0L1E"],"startyear":"2024","endyear":"2026","registrationkey":"{KEY}"} | W66: Registration key (free) | X66: Free (500 req/day w/ key) | Y66: JSON | Z66: Primary | AA66: CPI surprise is now actual (this source) minus the Cleveland Fed nowcast (DS-90) instead of Wall Street consensus. | AB66: One POST returns all CPI series | AC66: Release calendar
A67: DS-22 | B67: Monthly / on release | C67: M1 | D67: 1st business day of month, 08:00 | E67: 1st business day of month, 05:00 | F67: 1 | G67: 1 | H67: =F67*G67 -> 1 | I67: P1 | J67: 0 | K67: Free – no paid plan needed | L67: 0 | M67: 0 | N67: =IF(L67=0,"None",IF(M67>0.6,"High",IF(M67>0.2,"Medium","Low"))) -> None | O67: =J67+(L67-J67)*M67 -> 0 | Q67: Inflation | R67: CPI release schedule | S67: BLS | T67: Web / ICS | U67: https://www.bls.gov/schedule/news_release/cpi.htm | W67: None | X67: Free | Y67: HTML | Z67: Primary | AA67: FREE-TIER IMPACT: now a primary source of CPI release dates (replaces paid calendar DS-25). | AB67: Refresh CPI release dates | AC67: Release calendar
A68: DS-24 | B68: Monthly / on release | C68: M1 | D68: 08:35 on BEA PCE release day | E68: 05:35 on BEA PCE release day | F68: 1 | G68: 1 | H68: =F68*G68 -> 1 | I68: P2 | J68: 0 | K68: Free – no paid plan needed | L68: 0 | M68: 0 | N68: =IF(L68=0,"None",IF(M68>0.6,"High",IF(M68>0.2,"Medium","Low"))) -> None | O68: =J68+(L68-J68)*M68 -> 0 | Q68: Inflation | R68: PCE price index (Fed's preferred gauge) | S68: BEA API | T68: REST | U68: https://apps.bea.gov/api/data?UserID={KEY}&method=GetData&DataSetName=NIPA&TableName=T20804&Frequency=M&Year=2026 | W68: API key (free) | X68: Free | Y68: JSON | Z68: Optional | AA68: Not in original scope but moves rate expectations | AC68: Release calendar
A69: DS-34 | B69: Monthly / on release | C69: M1 | D69: 08:35 on Census trade release day | E69: 05:35 on Census trade release day | F69: 2 | G69: 1 | H69: =F69*G69 -> 2 | I69: P3 | J69: 0 | K69: Free – no paid plan needed | L69: 0 | M69: 0 | N69: =IF(L69=0,"None",IF(M69>0.6,"High",IF(M69>0.2,"Medium","Low"))) -> None | O69: =J69+(L69-J69)*M69 -> 0 | Q69: Tariffs | R69: US import/export volumes by HS code | S69: Census International Trade API | T69: REST | U69: https://api.census.gov/data/timeseries/intltrade/imports/hs?get=GEN_VAL_MO,CTY_NAME&I_COMMODITY=8703&time=2026-07 | V69: Exports: /intltrade/exports/hs | W69: API key (optional) | X69: Free | Y69: JSON | Z69: Optional | AA69: Measures real trade impact | AB69: Imports + exports | AC69: Release calendar
A70: DS-46 | B70: Monthly / on release | C70: M1 | D70: 1st Monday of month, 08:00 | E70: 1st Monday of month, 05:00 | F70: 2 | G70: 1 | H70: =F70*G70 -> 2 | I70: P1 | J70: 0 | K70: Free – no paid plan needed | L70: 0 | M70: 0 | N70: =IF(L70=0,"None",IF(M70>0.6,"High",IF(M70>0.2,"Medium","Low"))) -> None | O70: =J70+(L70-J70)*M70 -> 0 | Q70: Robotaxi – US federal | R70: Crash reports for driverless (ADS) vehicles incl. Tesla Robotaxi/Cybercab | S70: NHTSA Standing General Order 2021-01 | T70: CSV download | U70: https://static.nhtsa.gov/odi/ffdd/sgo-2021-01/SGO-2021-01_Incident_Reports_ADS.csv | V70: Filter Reporting Entity = Tesla; L2 file: .../SGO-2021-01_Incident_Reports_ADAS.csv (FSD Supervised) | W70: None | X70: Free | Y70: CSV | Z70: Primary | AA70: Archive files for pre-16-Jun-2025 data on https://www.nhtsa.gov/SGOCrashReporting | AB70: ADS + ADAS CSVs | AC70: Release calendar
A71: DS-92 | B71: Monthly / on release | C71: M1 | D71: On FINRA publication date (twice monthly), 08:00 | E71: On FINRA publication date (twice monthly), 05:00 | F71: 1 | G71: 2 | H71: =F71*G71 -> 2 | I71: P2 | J71: 0 | K71: Free – no paid plan needed | L71: 0 | M71: 0 | N71: =IF(L71=0,"None",IF(M71>0.6,"High",IF(M71>0.2,"Medium","Low"))) -> None | O71: =J71+(L71-J71)*M71 -> 0 | Q71: Short interest | R71: Short interest: shares short, days to cover, % change; % of float derived | S71: FINRA Query API – consolidated short interest | T71: REST (POST) | U71: https://api.finra.org/data/group/otcMarket/name/consolidatedShortInterest | V71: Body: compareFilters on symbolCode IN (TSLA, SPCX, …) and settlementDate; fields e.g. currentShortPositionQuantity, daysToCoverQuantity (confirm names in the FINRA API Console) | W71: Free FINRA API account (client credentials); confirm dataset entitlement | X71: Free (non-commercial) | Y71: JSON/CSV | Z71: Primary | AA71: Covers exchange-listed and OTC stocks. Twice monthly on FINRA publication dates (see Release Calendar tab). % of float = short shares ÷ float (shares outstanding from SEC dei:EntityCommonStockSharesOutstanding as proxy) | AB71: One call per publication returns all tracked tickers | AC71: Release calendar
A72: DS-11 | B72: Quarterly | C72: Q1 | D72: Day after Tesla earnings, 08:00 | E72: Day after Tesla earnings, 05:00 | F72: 1 | G72: 0.33 | H72: =F72*G72 -> 0.33 | I72: P1 | J72: 0 | K72: Free – no paid plan needed | L72: 0 | M72: 0 | N72: =IF(L72=0,"None",IF(M72>0.6,"High",IF(M72>0.2,"Medium","Low"))) -> None | O72: =J72+(L72-J72)*M72 -> 0 | Q72: Tesla fundamentals | R72: Structured financials incl. gross margin (GrossProfit ÷ Revenues), EPS | S72: SEC EDGAR XBRL Company Facts | T72: REST | U72: https://data.sec.gov/api/xbrl/companyfacts/CIK0001318605.json | V72: Concepts us-gaap:GrossProfit and us-gaap:Revenues (gross margin = ratio, per quarter); single concept: /api/xbrl/companyconcept/CIK0001318605/us-gaap/GrossProfit.json | W72: None (User-Agent header) | X72: Free | Y72: JSON | Z72: Primary | AA72: Gross margin computed per fiscal quarter from 10-Q/10-K facts (Q4 = FY − 9M when only annual is reported) | AC72: US-MKT (NYSE trading days)
A73: DS-12 | B73: Quarterly | C73: Q1 | D73: Deliveries: ~2nd day after quarter end, 09:05; earnings: 16:35 | E73: Deliveries: ~2nd day after quarter end, 06:05; earnings: 13:35 | F73: 1 | G73: 0.67 | H73: =F73*G73 -> 0.67 | I73: P1 | J73: 0 | K73: Free – no paid plan needed | L73: 0 | M73: 0 | N73: =IF(L73=0,"None",IF(M73>0.6,"High",IF(M73>0.2,"Medium","Low"))) -> None | O73: =J73+(L73-J73)*M73 -> 0 | Q73: Tesla fundamentals | R73: Quarterly deliveries & production; shareholder deck incl. FSD active subscribers (where disclosed) | S73: Tesla Investor Relations | T73: Web | U73: https://ir.tesla.com/ | V73: Deliveries press release ~2nd day after quarter end; shareholder deck with earnings | W73: None | X73: Free | Y73: HTML/PDF | Z73: Primary | AA73: UI plots deliveries on their release date (~2nd day after quarter end), not quarter end. FSD active subscribers: quarterly, only where Tesla discloses it; may need manual entry if the deck is not structured | AB73: 2 events per quarter | AC73: US-MKT (NYSE trading days)
A74: DS-53 | B74: Quarterly | C74: Q1 | D74: When CPUC posts quarterly AV data | E74: When CPUC posts quarterly AV data | F74: 1 | G74: 0.33 | H74: =F74*G74 -> 0.33 | I74: P2 | J74: 0 | K74: Free – no paid plan needed | L74: 0 | M74: 0 | N74: =IF(L74=0,"None",IF(M74>0.6,"High",IF(M74>0.2,"Medium","Low"))) -> None | O74: =J74+(L74-J74)*M74 -> 0 | Q74: Robotaxi – California | R74: Passenger-carrying permits (Tesla TCP0046782-A) & AV quarterly data | S74: California Public Utilities Commission (CPUC) | T74: Web | U74: https://www.cpuc.ca.gov/regulatory-services/licensing/transportation-licensing-and-analysis-branch/autonomous-vehicle-programs | V74: Quarterly AV program data reports (trips, miles, incidents) for deployment permit holders | W74: None | X74: Free | Y74: XLSX/PDF | Z74: Primary | AA74: Bay Area service runs under charter-party (limo) permit, not AV deployment | AC74: US-MKT (NYSE trading days)
A75: DS-75 | B75: Quarterly | C75: Q1 | D75: Day after SPCX earnings, 08:00 | E75: Day after SPCX earnings, 05:00 | F75: 1 | G75: 0.33 | H75: =F75*G75 -> 0.33 | I75: P1 | J75: 0 | K75: Free – no paid plan needed | L75: 0 | M75: 0 | N75: =IF(L75=0,"None",IF(M75>0.6,"High",IF(M75>0.2,"Medium","Low"))) -> None | O75: =J75+(L75-J75)*M75 -> 0 | Q75: SpaceX customers | R75: Backlog, Starlink subscribers, revenue by segment | S75: SEC EDGAR – SPCX 10-Q/10-K/8-K | T75: REST | U75: https://data.sec.gov/submissions/CIK{SPCX CIK}.json | V75: XBRL: /api/xbrl/companyfacts/CIK{SPCX CIK}.json; resolve CIK via company_tickers.json | W75: None (User-Agent) | X75: Free | Y75: JSON | Z75: Primary | AA75: Remaining performance obligations = order backlog | AB75: XBRL backlog/subscribers; 8-K watch covered by DS-06 | AC75: US-MKT (NYSE trading days)
A76: DS-52 | B76: Annual | C76: A1 | D76: On publication (early in the year); holiday lists each December | E76: — | F76: 1 | G76: 0.083333333 | H76: =F76*G76 -> 0.083333333 | I76: P3 | J76: 0 | K76: Free – no paid plan needed | L76: 0 | M76: 0 | N76: =IF(L76=0,"None",IF(M76>0.6,"High",IF(M76>0.2,"Medium","Low"))) -> None | O76: =J76+(L76-J76)*M76 -> 0 | Q76: Robotaxi – California | R76: Annual disengagement & mileage reports | S76: California DMV | T76: Web (XLSX/CSV) | U76: https://www.dmv.ca.gov/portal/vehicle-industry-services/autonomous-vehicles/disengagement-reports/ | V76: Reporting period Dec 1–Nov 30; published early each year | W76: None | X76: Free | Y76: XLSX/CSV | Z76: Primary | AC76: —
A77: DS-83 | B77: Annual | C77: A1 | D77: On publication (early in the year); holiday lists each December | E77: — | F77: 1 | G77: 0.083333333 | H77: =F77*G77 -> 0.083333333 | I77: P2 | J77: 0 | K77: Free – no paid plan needed | L77: 0 | M77: 0 | N77: =IF(L77=0,"None",IF(M77>0.6,"High",IF(M77>0.2,"Medium","Low"))) -> None | O77: =J77+(L77-J77)*M77 -> 0 | Q77: Calendars | R77: Official NYSE holiday & early-close list | S77: NYSE | T77: Web | U77: https://www.nyse.com/markets/hours-calendars | V77: Published ~3 years ahead | W77: None | X77: Free | Y77: HTML | Z77: Secondary | AA77: Annual check against the library | AB77: December check of next year's list | AC77: —
A78: DS-84 | B78: Annual | C78: A1 | D78: On publication (early in the year); holiday lists each December | E78: — | F78: 1 | G78: 0.083333333 | H78: =F78*G78 -> 0.083333333 | I78: P2 | J78: 0 | K78: Free – no paid plan needed | L78: 0 | M78: 0 | N78: =IF(L78=0,"None",IF(M78>0.6,"High",IF(M78>0.2,"Medium","Low"))) -> None | O78: =J78+(L78-J78)*M78 -> 0 | Q78: Calendars | R78: US bond-market (SIFMA) closures & early closes | S78: SIFMA holiday recommendations | T78: Web | U78: https://www.sifma.org/resources/general/holiday-schedule/ | V78: Governs Treasury yield & NY Fed rate publication days | W78: None | X78: Free | Y78: HTML | Z78: Secondary | AA78: Bond market closes on Columbus & Veterans Day even though stocks trade | AB78: December check | AC78: —
A79: DS-85 | B79: Annual | C79: A1 | D79: On publication (early in the year); holiday lists each December | E79: — | F79: 1 | G79: 0.083333333 | H79: =F79*G79 -> 0.083333333 | I79: P3 | J79: 0 | K79: Free – no paid plan needed | L79: 0 | M79: 0 | N79: =IF(L79=0,"None",IF(M79>0.6,"High",IF(M79>0.2,"Medium","Low"))) -> None | O79: =J79+(L79-J79)*M79 -> 0 | Q79: Calendars | R79: US federal holidays (agency publishing days) | S79: US Office of Personnel Management (OPM) | T79: Web | U79: https://www.opm.gov/policy-data-oversight/pay-leave/federal-holidays/ | W79: None | X79: Free | Y79: HTML | Z79: Backup | AA79: Annual check | AB79: December check | AC79: —
A80: DS-86 | B80: Annual | C80: A1 | D80: On publication (early in the year); holiday lists each December | E80: — | F80: 1 | G80: 0.083333333 | H80: =F80*G80 -> 0.083333333 | I80: P2 | J80: 0 | K80: Free – no paid plan needed | L80: 0 | M80: 0 | N80: =IF(L80=0,"None",IF(M80>0.6,"High",IF(M80>0.2,"Medium","Low"))) -> None | O80: =J80+(L80-J80)*M80 -> 0 | Q80: Calendars | R80: China public holidays & weekend make-up workdays | S80: State Council General Office (gov.cn) | T80: Web | U80: https://www.gov.cn/zhengce/ | V80: Annual holiday notice (usually Nov–Dec for the next year) | W80: None | X80: Free | Y80: HTML (Chinese) | Z80: Secondary | AA80: Used to skip MOFCOM/MIIT sources on China holidays | AB80: Check when the notice is published (usually Nov–Dec) | AC80: —
A81: DS-05 | B81: One-time | C81: O1 | D81: At setup + when a user adds a ticker | E81: At setup + when a user adds a ticker | F81: 9 | G81: 0 | H81: =F81*G81 -> 0 | I81: P3 | J81: 0 | K81: Free – no paid plan needed | L81: 0 | M81: 0 | N81: =IF(L81=0,"None",IF(M81>0.6,"High",IF(M81>0.2,"Medium","Low"))) -> None | O81: =J81+(L81-J81)*M81 -> 0 | Q81: Stock price | R81: 5-year daily history backfill per ticker | S81: Yahoo Finance | T81: REST (unofficial) | U81: https://query1.finance.yahoo.com/v8/finance/chart/{TICKER}?interval=1d&range=5y | V81: Python: yfinance; one call per ticker at setup (9 tickers) and again whenever a user adds a ticker | W81: None | X81: Free | Y81: JSON | Z81: Fallback | AA81: Unofficial, no SLA, may throttle. Used only for one-time backfill (not polled); adjusted closes – store split/dividend-adjusted and raw | AB81: 5-year daily backfill: one call per ticker (9 at setup); no recurring calls | AC81: US-MKT (NYSE trading days)
A82: DS-07 | B82: One-time | C82: O1 | D82: At setup | E82: — | F82: 0 | G82: 0 | H82: =F82*G82 -> 0 | I82: P3 | J82: 0 | K82: Free – no paid plan needed | L82: 0 | M82: 0 | N82: =IF(L82=0,"None",IF(M82>0.6,"High",IF(M82>0.2,"Medium","Low"))) -> None | O82: =J82+(L82-J82)*M82 -> 0 | Q82: SpaceX valuation / listing | R82: Pre-IPO tender/secondary price history (historical only) | S82: Forge Global / Nasdaq Private Market | T82: Web | U82: https://forgeglobal.com/spacex_stock/ ; https://www.nasdaqprivatemarket.com/company/spacex/ | V82: One-time backfill of pre-IPO valuations | W82: Account for detail | X82: Free summary | Y82: HTML | Z82: Reference | AA82: Only needed for pre-June-2026 history | AB82: Pre-IPO history only | AC82: —
A83: DS-03 | B83: Failover only | C83: F1 | D83: Only when the primary source fails | E83: — | F83: 2 | G83: 0 | H83: =F83*G83 -> 0 | I83: P3 | J83: 0 | K83: Free – no paid plan needed | L83: 0 | M83: 0 | N83: =IF(L83=0,"None",IF(M83>0.6,"High",IF(M83>0.2,"Medium","Low"))) -> None | O83: =J83+(L83-J83)*M83 -> 0 | Q83: Stock price | R83: Latest quote; daily series | S83: Alpha Vantage | T83: REST | U83: https://www.alphavantage.co/query?function=GLOBAL_QUOTE&symbol=TSLA&apikey={KEY} | V83: Hourly GLOBAL_QUOTE for TSLA+SPCX ≈ 14 calls/day; TIME_SERIES_DAILY for EOD | W83: API key | X83: Free 25 req/day; paid tiers | Y83: JSON/CSV | Z83: Backup | AA83: FREE-TIER IMPACT: shares the 25 calls/day free limit with DS-40 news; only used if Alpaca and Massive both fail. | AC83: US-MKT (NYSE trading days)
A84: DS-04 | B84: Failover only | C84: F1 | D84: Only when the primary source fails | E84: — | F84: 2 | G84: 0 | H84: =F84*G84 -> 0 | I84: P3 | J84: 0 | K84: Free – no paid plan needed | L84: 0 | M84: 0 | N84: =IF(L84=0,"None",IF(M84>0.6,"High",IF(M84>0.2,"Medium","Low"))) -> None | O84: =J84+(L84-J84)*M84 -> 0 | Q84: Stock price | R84: Quote | S84: Finnhub | T84: REST | U84: https://finnhub.io/api/v1/quote?symbol=TSLA&token={KEY} | V84: One call per ticker per hour | W84: API key | X84: Free 60 req/min | Y84: JSON | Z84: Backup | AA84: FREE-TIER IMPACT: none – free 60 calls/min covers failover quotes. | AC84: US-MKT (NYSE trading days)
A85: DS-23 | B85: Failover only | C85: F1 | D85: Only when the primary source fails | E85: — | F85: 4 | G85: 0 | H85: =F85*G85 -> 0 | I85: P3 | J85: 0 | K85: Free – no paid plan needed | L85: 0 | M85: 0 | N85: =IF(L85=0,"None",IF(M85>0.6,"High",IF(M85>0.2,"Medium","Low"))) -> None | O85: =J85+(L85-J85)*M85 -> 0 | Q85: Inflation | R85: CPI, core CPI, PCE, core PCE, breakeven inflation | S85: FRED | T85: REST | U85: https://api.stlouisfed.org/fred/series/observations?series_id=CPIAUCSL&api_key={KEY}&file_type=json | V85: CPIAUCSL, CPILFESL, PCEPI, PCEPILFE, T10YIE | W85: API key | X85: Free | Y85: JSON | Z85: Backup | AA85: FRED release dates: /fred/release/dates?release_id=10 (CPI) | AB85: Backup for BLS/BEA | AC85: US-FED (US federal business days)
A86: DS-42 | B86: Failover only | C86: F1 | D86: Only when the primary source fails | E86: — | F86: 1 | G86: 0 | H86: =F86*G86 -> 0 | I86: P3 | J86: 0 | K86: Free – no paid plan needed | L86: 0 | M86: 0 | N86: =IF(L86=0,"None",IF(M86>0.6,"High",IF(M86>0.2,"Medium","Low"))) -> None | O86: =J86+(L86-J86)*M86 -> 0 | Q86: Financial news | R86: Ticker news | S86: Massive (Polygon) News | T86: REST | U86: https://api.massive.com/v2/reference/news?ticker=TSLA&limit=50 | V86: Includes per-ticker sentiment insights | W86: API key | X86: Included in plan | Y86: JSON | Z86: Backup | AC86: US-MKT (NYSE trading days)
A87: DS-87 | B87: Failover only | C87: F1 | D87: Only when the primary source fails | E87: — | F87: 3 | G87: 0 | H87: =F87*G87 -> 0 | I87: P3 | J87: 0 | K87: Free – no paid plan needed | L87: 0 | M87: 0 | N87: =IF(L87=0,"None",IF(M87>0.6,"High",IF(M87>0.2,"Medium","Low"))) -> None | O87: =J87+(L87-J87)*M87 -> 0 | Q87: Calendars | R87: Public holidays by country (backup) | S87: Nager.Date API | T87: REST | U87: https://date.nager.at/api/v3/PublicHolidays/{year}/{US|CN|NL} | W87: None | X87: Free | Y87: JSON | Z87: Backup | AA87: Only if the Python library is unavailable | AB87: US, CN, NL | AC87: Same as primary
A88: DS-91 | B88: Failover only | C88: F1 | D88: Only when the primary source fails | E88: — | F88: 3 | G88: 0 | H88: =F88*G88 -> 0 | I88: P3 | J88: 0 | K88: Free – no paid plan needed | L88: 0 | M88: 0 | N88: =IF(L88=0,"None",IF(M88>0.6,"High",IF(M88>0.2,"Medium","Low"))) -> None | O88: =J88+(L88-J88)*M88 -> 0 | Q88: Stock price | R88: Daily index closes (fallback for ETF proxies): S&P 500, Dow, Nasdaq-100 | S88: FRED | T88: REST | U88: https://api.stlouisfed.org/fred/series/observations?series_id=SP500&api_key={KEY}&file_type=json | V88: series_id = SP500, DJIA, NASDAQ100 (Russell 2000 and sector indexes not on FRED – use DS-01/DS-05) | W88: API key (free) | X88: Free | Y88: JSON | Z88: Backup | AA88: Index levels, not ETF prices; one-day lag. Used only if Alpaca and Massive both fail | AB88: SP500, DJIA, NASDAQ100 | AC88: US-FED (US federal business days)
A89: DS-20 | B89: Not used / merged | C89: X0 | D89: See Schedule Note | E89: — | F89: 0 | G89: 0 | H89: =F89*G89 -> 0 | I89: — | J89: 0 | K89: Not used – free tier only ($0 data budget) | L89: 0 | M89: 0 | N89: =IF(L89=0,"None",IF(M89>0.6,"High",IF(M89>0.2,"Medium","Low"))) -> None | O89: =J89+(L89-J89)*M89 -> 0 | P89: Atlanta Fed Market Probability Tracker (DS-88) + Kalshi Fed-decision odds (DS-89) | Q89: Interest rates | R89: Market-implied rate-change probabilities | S89: CME FedWatch | T89: Web / paid API | U89: https://www.cmegroup.com/markets/interest-rates/cme-fedwatch-tool.html | V89: API via CME DataMine / FedWatch API subscription | W89: Subscription for API | X89: Paid API; web free | Y89: HTML/JSON | Z89: Not used (paid) | AA89: FREE-TIER IMPACT: paid API dropped. Meeting-by-meeting FedWatch odds are no longer collected; replaced by Atlanta Fed quarterly-horizon probabilities (DS-88) and Kalshi meeting odds (DS-89). | AB89: Paid API not used – replaced by DS-88 (Atlanta Fed) and DS-89 (Kalshi) | AC89: —
A90: DS-25 | B90: Not used / merged | C90: X0 | D90: See Schedule Note | E90: — | F90: 0 | G90: 0 | H90: =F90*G90 -> 0 | I90: — | J90: 0 | K90: Not used – free tier only ($0 data budget) | L90: 0 | M90: 0 | N90: =IF(L90=0,"None",IF(M90>0.6,"High",IF(M90>0.2,"Medium","Low"))) -> None | O90: =J90+(L90-J90)*M90 -> 0 | P90: Release dates: BLS schedule (DS-22) + FRED releases (DS-26). Expectations: Cleveland Fed nowcast (DS-90) + Kalshi CPI odds (DS-89) | Q90: Economic calendar | R90: Upcoming macro releases w/ consensus vs actual | S90: Finnhub | T90: REST | U90: https://finnhub.io/api/v1/calendar/economic?token={KEY} | W90: API key | X90: Paid (premium endpoint) | Y90: JSON | Z90: Not used (paid) | AA90: FREE-TIER IMPACT: paid calendar dropped. No consensus forecasts: release dates come from DS-22/DS-26 and expectations from the Cleveland Fed nowcast (DS-90), so 'surprise' is measured vs a model, not analysts. | AB90: Paid calendar not used – dates from DS-22/DS-26, expectations from DS-90 (and DS-89) | AC90: —
A91: DS-43 | B91: Not used / merged | C91: X0 | D91: See Schedule Note | E91: — | F91: 0 | G91: 0 | H91: =F91*G91 -> 0 | I91: — | J91: 0 | K91: Not used – free tier only ($0 data budget) | L91: 0 | M91: 0 | N91: =IF(L91=0,"None",IF(M91>0.6,"High",IF(M91>0.2,"Medium","Low"))) -> None | O91: =J91+(L91-J91)*M91 -> 0 | P91: Dropped – Finnhub company news (DS-41) + Google News RSS (DS-44) | Q91: Financial news | R91: Broad headline search | S91: NewsAPI | T91: REST | U91: https://newsapi.org/v2/everything?q=Tesla OR SpaceX&sortBy=publishedAt&apiKey={KEY} | W91: API key | X91: Free dev (24h delay); paid prod | Y91: JSON | Z91: Not used (paid) | AA91: FREE-TIER IMPACT: not used. Free Developer tier is 24h delayed and not licensed for production; news comes from Finnhub (DS-41) and Google News RSS (DS-44). | AB91: Not used – free tier is 24h delayed and not licensed for production; news covered by DS-41, DS-44 | AC91: US-MKT (NYSE trading days)
A92: DS-49 | B92: Not used / merged | C92: X0 | D92: See Schedule Note | E92: — | F92: 0 | G92: 0 | H92: =F92*G92 -> 0 | I92: — | J92: 0 | K92: Free – no paid plan needed | L92: 0 | M92: 0 | N92: =IF(L92=0,"None",IF(M92>0.6,"High",IF(M92>0.2,"Medium","Low"))) -> None | O92: =J92+(L92-J92)*M92 -> 0 | Q92: Robotaxi – US federal | R92: FMVSS exemptions (Cybercab has no steering wheel/pedals) | S92: NHTSA via Federal Register API | T92: REST | U92: https://www.federalregister.gov/api/v1/documents.json?conditions[term]=Tesla exemption&conditions[agencies][]=national-highway-traffic-safety-administration | V92: Also AV framework rulemakings (AV STEP) | W92: None | X92: Free | Y92: JSON | Z92: Primary | AA92: Exemption cap limits Cybercab volume | AB92: Covered by DS-27 Federal Register query | AC92: —
A93: DS-78 | B93: Not used / merged | C93: X0 | D93: See Schedule Note | E93: — | F93: 0 | G93: 0 | H93: =F93*G93 -> 0 | I93: — | J93: 0 | K93: Free – no paid plan needed | L93: 0 | M93: 0 | N93: =IF(L93=0,"None",IF(M93>0.6,"High",IF(M93>0.2,"Medium","Low"))) -> None | O93: =J93+(L93-J93)*M93 -> 0 | Q93: SpaceX news | R93: SPCX ticker news + sentiment | S93: Finnhub / Alpha Vantage / Massive | T93: REST | U93: https://finnhub.io/api/v1/company-news?symbol=SPCX&from={d}&to={d}&token={KEY} | V93: AV: function=NEWS_SENTIMENT&tickers=SPCX | W93: API key | X93: Free tiers | Y93: JSON | Z93: Primary | AA93: Reuse existing news agents with SPCX ticker | AB93: SPCX added to DS-40/DS-41 calls | AC93: —
A94: DS-79 | B94: Not used / merged | C94: X0 | D94: See Schedule Note | E94: — | F94: 0 | G94: 0 | H94: =F94*G94 -> 0 | I94: — | J94: 0 | K94: Free – no paid plan needed | L94: 0 | M94: 0 | N94: =IF(L94=0,"None",IF(M94>0.6,"High",IF(M94>0.2,"Medium","Low"))) -> None | O94: =J94+(L94-J94)*M94 -> 0 | Q94: SpaceX news | R94: Headline RSS (SpaceX, Starship, Starlink, NASA contract) | S94: Google News RSS | T94: RSS | U94: https://news.google.com/rss/search?q=SpaceX+OR+Starlink+OR+Starship&hl=en-US&gl=US&ceid=US:en | V94: Robotaxi feed: q=Tesla+Robotaxi+OR+Cybercab | W94: None | X94: Free | Y94: RSS XML | Z94: Backup | AB94: Covered by DS-44 Google News RSS queries | AC94: —

Sheet Cost Summary
A1: Monthly data cost by priority
A2: Priority | B2: Meaning | C2: # Sources | D2: Current ($/mo) | E2: Worst Case – all paid plans ($/mo) | F2: Expected ($/mo, probability-weighted)
A3: P1 | B3: Must-have: dashboard is wrong or incomplete without it | C3: =COUNTIF('Data Sources'!$I$2:$I$94,A3) -> 30 | D3: =SUMIFS('Data Sources'!$J$2:$J$94,'Data Sources'!$I$2:$I$94,A3) -> 0 | E3: =SUMIFS('Data Sources'!$L$2:$L$94,'Data Sources'!$I$2:$I$94,A3) -> 0 | F3: =SUMIFS('Data Sources'!$O$2:$O$94,'Data Sources'!$I$2:$I$94,A3) -> 0
A4: P2 | B4: Should-have: improves signal; dashboard works without it | C4: =COUNTIF('Data Sources'!$I$2:$I$94,A4) -> 33 | D4: =SUMIFS('Data Sources'!$J$2:$J$94,'Data Sources'!$I$2:$I$94,A4) -> 0 | E4: =SUMIFS('Data Sources'!$L$2:$L$94,'Data Sources'!$I$2:$I$94,A4) -> 0 | F4: =SUMIFS('Data Sources'!$O$2:$O$94,'Data Sources'!$I$2:$I$94,A4) -> 0
A5: P3 | B5: Nice-to-have / backup / cross-check | C5: =COUNTIF('Data Sources'!$I$2:$I$94,A5) -> 24 | D5: =SUMIFS('Data Sources'!$J$2:$J$94,'Data Sources'!$I$2:$I$94,A5) -> 0 | E5: =SUMIFS('Data Sources'!$L$2:$L$94,'Data Sources'!$I$2:$I$94,A5) -> 0 | F5: =SUMIFS('Data Sources'!$O$2:$O$94,'Data Sources'!$I$2:$I$94,A5) -> 0
A6: TOTAL | C6: =SUM(C3:C5) -> 87 | D6: =SUM(D3:D5) -> 0 | E6: =SUM(E3:E5) -> 0 | F6: =SUM(F3:F5) -> 0
A8: Paid upgrades declined – free replacements in use
A9: ID | B9: Source | C9: Priority | D9: Paid Plan Declined | E9: Price Avoided ($/mo) | H9: Free Replacement / How the Free Tier Is Used
A10: DS-25 | B10: Finnhub | C10: P1 | D10: FMP Premium / Finnhub premium economic calendar | E10: 59 | H10: Release dates: BLS schedule (DS-22) + FRED releases (DS-26). Expectations: Cleveland Fed nowcast (DS-90) + Kalshi CPI odds (DS-89)
A11: DS-01 | B11: Massive (formerly Polygon.io) | C11: P1 | D11: Massive Stocks Starter | E11: 29 | H11: Alpaca free IEX hourly bars (DS-02) become primary; Massive free tier keeps the daily-close check
A12: DS-20 | B12: CME FedWatch | C12: P2 | D12: CME FedWatch API – end of day | E12: 25 | H12: Atlanta Fed Market Probability Tracker (DS-88) + Kalshi Fed-decision odds (DS-89)
A13: DS-40 | B13: Alpha Vantage NEWS_SENTIMENT | C13: P2 | D13: Alpha Vantage Premium | E13: 49.99 | H13: Stay on free 25 calls/day: news polling capped at 16 calls/day
A14: DS-02 | B14: Alpaca Market Data | C14: P3 | D14: Alpaca Algo Trader Plus (SIP feed) | E14: 99 | H14: Use free IEX feed; full-market volume not required for hourly trend
A15: DS-43 | B15: NewsAPI | C15: P3 | D15: NewsAPI Business | E15: 449 | H15: Dropped – Finnhub company news (DS-41) + Google News RSS (DS-44)
A16: DS-08 | B16: The Space Devs – Launch Library 2 | C16: P2 | D16: Launch Library 2 Patreon tier (est.) | E16: 5 | H16: Free 15 calls/hour; we use 1/hour
A17: DS-36 | B17: ACLED API | C17: P3 | D17: ACLED Partner/Enterprise (unpriced) | E17: 0 | H17: Open tier (aggregated data) + GDELT events (DS-35)
A18: TOTAL AVOIDED | E18: =SUM(E10:E17) -> 715.99
A20: Policy (2026-10-03): $0 data budget – every source runs on its free tier. Paid Plan Cost and Likelihood of Paying are 0 on every row; to reconsider an upgrade, enter its price and likelihood on Data Sources and these totals recalculate.
A21: Trade-offs accepted: IEX-only volume (prices unaffected); quarterly-horizon rate odds from Atlanta Fed plus prediction-market odds instead of FedWatch meeting odds; Cleveland Fed nowcast instead of Wall Street consensus for CPI surprise; news capped at free limits.
A22: Prices checked 2026-10-03 from provider pricing pages / published summaries. FMP price is billed annually; Launch Library tier price is an estimate; ACLED commercial pricing is unpublished (excluded).
A23: Not included: hosting, database and scheduler costs for running the agents.

Sheet Batch Schedule
A1: Job | B1: Cadence | C1: Job Name | D1: Run Time (ET) | E1: Run Time (PT) | F1: Days | G1: Source IDs | H1: Runs / Month | I1: Calls / Run (sum) | J1: Calls / Month | K1: Avg Calls / Day | L1: Writes To | M1: Holiday Calendar
A2: H1 | B2: Hourly | C2: Market prices | D2: Hourly at :05, 10:05–16:05 (early-close days: 10:05–13:05) | E2: Hourly at :05, 07:05–13:05 (early-close days: 07:05–10:05) | F2: NYSE trading days only | G2: DS-02 | H2: 145.91667 | I2: =SUMIFS('Data Sources'!$F$2:$F$94,'Data Sources'!$C$2:$C$94,A2) -> 1 | J2: =SUMIFS('Data Sources'!$H$2:$H$94,'Data Sources'!$C$2:$C$94,A2) -> 145.91667 | K2: =J2/30 -> 4.8638889 | L2: prices_hourly (1-hour bars; last run = daily close) | M2: US-MKT (NYSE trading days)
A3: H2 | B3: Hourly | C3: News & sentiment | D3: Hourly at :15, 24 runs | E3: Hourly at :15, 24 runs | F3: NYSE trading days only; first run after a weekend/holiday pulls everything since the last run | G3: DS-35, DS-40, DS-41, DS-44, DS-77 | H3: 502 | I3: =SUMIFS('Data Sources'!$F$2:$F$94,'Data Sources'!$C$2:$C$94,A3) -> 8 | J3: =SUMIFS('Data Sources'!$H$2:$H$94,'Data Sources'!$C$2:$C$94,A3) -> 3848.6667 | K3: =J3/30 -> 128.28889 | L3: news_articles (dedupe on URL hash) | M3: US-MKT (NYSE trading days)
A4: H3 | B4: Hourly | C4: Regulatory & company feeds | D4: Hourly at :25, 06:25–22:25 | E4: Hourly at :25, 03:25–19:25 | F4: US federal business days; catch-up on first run after a gap | G4: DS-06, DS-08, DS-09, DS-10, DS-18, DS-27, DS-28, DS-29, DS-72 | H4: 354.16667 | I4: =SUMIFS('Data Sources'!$F$2:$F$94,'Data Sources'!$C$2:$C$94,A4) -> 9 | J4: =SUMIFS('Data Sources'!$H$2:$H$94,'Data Sources'!$C$2:$C$94,A4) -> 3187.5 | K4: =J4/30 -> 106.25 | L4: events (event_ts, type, source_url) + filings | M4: US-FED (US federal business days)
A5: D1 | B5: Daily | C5: Morning macro & calendars | D5: 07:00 | E5: 04:00 | F5: US federal business days | G5: DS-13, DS-15, DS-16, DS-26, DS-39, DS-45, DS-88 | H5: 20.833333 | I5: =SUMIFS('Data Sources'!$F$2:$F$94,'Data Sources'!$C$2:$C$94,A5) -> 17 | J5: =SUMIFS('Data Sources'!$H$2:$H$94,'Data Sources'!$C$2:$C$94,A5) -> 354.16667 | K5: =J5/30 -> 11.805556 | L5: macro_daily, release_calendar | M5: US-FED (US federal business days)
A6: D2 | B6: Daily | C6: Regulatory & operations sweep | D6: 07:30 | E6: 04:30 | F6: US federal business days; China/NL sources skipped on their own holidays | G6: DS-31, DS-32, DS-33, DS-37, DS-47, DS-48, DS-60, DS-61, DS-64, DS-65, DS-71, DS-74, DS-76 | H6: 20.833333 | I6: =SUMIFS('Data Sources'!$F$2:$F$94,'Data Sources'!$C$2:$C$94,A6) -> 15 | J6: =SUMIFS('Data Sources'!$H$2:$H$94,'Data Sources'!$C$2:$C$94,A6) -> 312.5 | K6: =J6/30 -> 10.416667 | L6: events, robotaxi_fleet, launches | M6: US-FED (US federal business days)
A7: D3 | B7: Daily | C7: Overnight rates | D7: 09:15 | E7: 06:15 | F7: US federal business days | G7: DS-17 | H7: 20.833333 | I7: =SUMIFS('Data Sources'!$F$2:$F$94,'Data Sources'!$C$2:$C$94,A7) -> 2 | J7: =SUMIFS('Data Sources'!$H$2:$H$94,'Data Sources'!$C$2:$C$94,A7) -> 41.666667 | K7: =J7/30 -> 1.3888889 | L7: macro_daily | M7: US-FED (US federal business days)
A8: D4 | B8: Daily | C8: Market close | D8: 16:45 | E8: 13:45 | F8: US bond-market (SIFMA) business days | G8: DS-01, DS-14, DS-89, DS-90, DS-93 | H8: 20.75 | I8: =SUMIFS('Data Sources'!$F$2:$F$94,'Data Sources'!$C$2:$C$94,A8) -> 15 | J8: =SUMIFS('Data Sources'!$H$2:$H$94,'Data Sources'!$C$2:$C$94,A8) -> 311.25 | K8: =J8/30 -> 10.375 | L8: macro_daily (yield curve, FedWatch odds) | M8: US-BOND (SIFMA bond-market days)
A9: D5 | B9: Daily | C9: Government contracts | D9: 17:45 | E9: 14:45 | F9: US federal business days | G9: DS-67, DS-68, DS-69, DS-70 | H9: 20.833333 | I9: =SUMIFS('Data Sources'!$F$2:$F$94,'Data Sources'!$C$2:$C$94,A9) -> 4 | J9: =SUMIFS('Data Sources'!$H$2:$H$94,'Data Sources'!$C$2:$C$94,A9) -> 83.333333 | K9: =J9/30 -> 2.7777778 | L9: contracts (award_id, agency, obligated $) | M9: US-FED (US federal business days)
A10: W1 | B10: Weekly | C10: Weekly sweep | D10: Mon 08:00 | E10: Mon 05:00 | F10: Monday; if Monday is a US federal holiday, runs the next business day | G10: DS-30, DS-36, DS-38, DS-50, DS-51, DS-54, DS-55, DS-56, DS-57, DS-58, DS-59, DS-62, DS-63, DS-66, DS-73 | H10: 4.33 | I10: =SUMIFS('Data Sources'!$F$2:$F$94,'Data Sources'!$C$2:$C$94,A10) -> 15 | J10: =SUMIFS('Data Sources'!$H$2:$H$94,'Data Sources'!$C$2:$C$94,A10) -> 64.95 | K10: =J10/30 -> 2.165 | L10: events, robotaxi_fleet, risk_indices | M10: US-FED (US federal business days)
A11: M1 | B11: Monthly / on release | C11: Release-triggered | D11: At release time (see Run Time); dates come from D1 calendars | E11: 3 hours earlier than ET | F11: Release days only (agencies don't release on holidays) | G11: DS-19, DS-21, DS-22, DS-24, DS-34, DS-46, DS-92 | H11: 1 | I11: =SUMIFS('Data Sources'!$F$2:$F$94,'Data Sources'!$C$2:$C$94,A11) -> 9 | J11: =SUMIFS('Data Sources'!$H$2:$H$94,'Data Sources'!$C$2:$C$94,A11) -> 10 | K11: =J11/30 -> 0.33333333 | L11: releases (actual, consensus, surprise, release_ts) | M11: Release calendar
A12: C1 | B12: Monthly / on release | C12: Calendar refresh | D12: 1st US federal business day of month, 06:00 | E12: 03:00 | F12: 1st US federal business day of month | G12: DS-80, DS-81, DS-82 | H12: 1 | I12: =SUMIFS('Data Sources'!$F$2:$F$94,'Data Sources'!$C$2:$C$94,A12) -> 1 | J12: =SUMIFS('Data Sources'!$H$2:$H$94,'Data Sources'!$C$2:$C$94,A12) -> 1 | K12: =J12/30 -> 0.033333333 | L12: calendar_days (date, calendar, is_open, close_time) | M12: US-FED (US federal business days)
A13: Q1 | B13: Quarterly | C13: Earnings & quarterly reports | D13: Earnings day 16:35 + next day 08:00 | E13: 13:35 + next day 05:00 | F13: Earnings / quarter-end (NYSE trading days) | G13: DS-11, DS-12, DS-53, DS-75 | H13: 0.33 | I13: =SUMIFS('Data Sources'!$F$2:$F$94,'Data Sources'!$C$2:$C$94,A13) -> 4 | J13: =SUMIFS('Data Sources'!$H$2:$H$94,'Data Sources'!$C$2:$C$94,A13) -> 1.66 | K13: =J13/30 -> 0.055333333 | L13: fundamentals_quarterly | M13: US-MKT (NYSE trading days)
... A17: X0 | B17: Not used / merged | C17: Not collected (paid) or merged into another call | D17: See Schedule Note | E17: — | F17: — | G17: DS-20, DS-25, DS-43, DS-49, DS-78, DS-79 | H17: 0 | I17: =SUMIFS('Data Sources'!$F$2:$F$94,'Data Sources'!$C$2:$C$94,A17) -> 0 | J17: =SUMIFS('Data Sources'!$H$2:$H$94,'Data Sources'!$C$2:$C$94,A17) -> 0 | K17: =J17/30 -> 0 | L17: — | M17: —
A18: TOTAL | J18: =SUM(J2:J17) -> 8363.0267 | K18: =SUM(K2:K17) -> 278.76756
A20: Free-tier limit check (typical day, after batching)
A21: Provider | B21: Free limit | C21: Our peak calls / day | D21: Headroom | G21: Source IDs
A22: Alpaca (free IEX + indicative options) | B22: 200 calls/min | C22: 9 | D22: OK | G22: DS-02 (7), DS-93 (2)
A23: Massive (free Basic) | B23: 5 calls/min | C23: 9 | D23: OK | G23: DS-01 (throttled: max 5/min)
A24: FINRA API (free) | B24: Not published – 1 call per publication | C24: 1 | D24: OK | G24: DS-92 (2/month)
A25: Kalshi (public data) | B25: ~20 calls/sec | C25: 2 | D25: OK | G25: DS-89
A26: Alpha Vantage | B26: 25 calls/day | C26: 16 | D26: OK | G26: DS-40
A27: Finnhub (free) | B27: 60 calls/min | C27: 50 | D27: OK | G27: DS-13, DS-41
A28: SAM.gov (basic key) | B28: 10 calls/day | C28: 2 | D28: OK | G28: DS-68, DS-69
A29: Launch Library 2 | B29: 15 calls/hour | C29: 17 | D29: OK — 1 call/hour vs 15/hour | G29: DS-08 (1/hour)
A30: FRED | B30: 120 calls/min | C30: 14 | D30: OK | G30: DS-15, 16, 39, 45
A31: SEC EDGAR | B31: 10 calls/sec | C31: 34 | D31: OK | G31: DS-06, DS-10
A32: BLS (with key) | B32: 500 calls/day | C32: 1 | D32: OK | G32: DS-21 (release days)

Sheet Holiday Calendar
A1: Date | B1: Day | C1: Calendar | D1: Holiday / Event | E1: Jobs Affected | F1: Sources Affected
A2: 46300 | B2: Mon | C2: CN | D2: China holiday – National Day (observed) | E2: D2 skips China sources | F2: DS-33, DS-59
A3: 46301 | B3: Tue | C3: CN | D3: China holiday – Day off (substituted from 09/20/2026) | E3: D2 skips China sources | F3: DS-33, DS-59
A4: 46302 | B4: Wed | C4: CN | D4: China holiday – Day off (substituted from 10/10/2026) | E4: D2 skips China sources | F4: DS-33, DS-59
A5: 46305 | B5: Sat | C5: CN | D5: China make-up workday (weekend working day) | E5: No US job runs on weekends; China sources picked up next US business day | F5: DS-33, DS-59
A6: 46307 | B6: Mon | C6: US-BOND | D6: Bond market closed (SIFMA) – Columbus Day | E6: D4 skips | F6: DS-14, DS-20
A7: 46307 | B7: Mon | C7: US-FED | D7: US federal holiday – Columbus Day | E7: H3, D1, D2, D3, D5 skip – W1 moves to Tue | F7: All US-FED sources
A8: 46337 | B8: Wed | C8: US-BOND | D8: Bond market closed (SIFMA) – Veterans Day | E8: D4 skips | F8: DS-14, DS-20
A9: 46337 | B9: Wed | C9: US-FED | D9: US federal holiday – Veterans Day | E9: H3, D1, D2, D3, D5 skip | F9: All US-FED sources
A10: 46352 | B10: Thu | C10: US-BOND | D10: Bond market closed (SIFMA) – Thanksgiving Day | E10: D4 skips | F10: DS-14, DS-20
A11: 46352 | B11: Thu | C11: US-FED | D11: US federal holiday – Thanksgiving Day | E11: H3, D1, D2, D3, D5 skip | F11: All US-FED sources
A12: 46352 | B12: Thu | C12: US-MKT | D12: NYSE closed – Thanksgiving Day | E12: H1, H2, Q1 skip | F12: All US-MKT sources
A13: 46353 | B13: Fri | C13: US-MKT | D13: NYSE early close (13:00 ET) | E13: H1 runs 10:05–13:05 ET only (last run = close) | F13: DS-01 and backups
... A73: 46752 | B73: Fri | C73: US-FED | D73: US federal holiday – New Year's Day (observed) | E73: H3, D1, D2, D3, D5 skip | F73: All US-FED sources
A75: Rule: no job runs on Saturday or Sunday. Each job also skips the holidays of the calendar named on its row in Data Sources / Batch Schedule.
A76: Generated 2026-10-03 from exchange_calendars (NYSE) and the holidays library (US federal, China, Netherlands). The agents use the same libraries at run time (DS-80, DS-81), so this list is for reference.
A77: US-FED holidays that fall on a weekday but not NYSE holidays (Columbus Day, Veterans Day): stock jobs run, federal and bond jobs skip.
A78: China 2027 dates are the library's projection; replace with the State Council notice when published (usually Nov–Dec 2026).
A79: Weekend-only holidays are not listed because nothing runs on weekends anyway.

Sheet Release Calendar
A1: Release | B1: Reference / Settlement Date | C1: Due Date | D1: Publication Date (collect) | E1: Job | F1: Source
A2: FINRA short interest | B2: 46295 | C2: 46297 | D2: 46304 | E2: M1 (08:00 ET next business day if after hours) | F2: DS-92
A3: FINRA short interest | B3: 46310 | C3: 46314 | D3: 46321 | E3: M1 (08:00 ET next business day if after hours) | F3: DS-92
A4: FINRA short interest | B4: 46325 | C4: 46329 | D4: 46336 | E4: M1 (08:00 ET next business day if after hours) | F4: DS-92
A5: FINRA short interest | B5: 46339 | C5: 46343 | D5: 46350 | E5: M1 (08:00 ET next business day if after hours) | F5: DS-92
A6: FINRA short interest | B6: 46356 | C6: 46358 | D6: 46365 | E6: M1 (08:00 ET next business day if after hours) | F6: DS-92
A7: FINRA short interest | B7: 46371 | C7: 46373 | D7: 46380 | E7: M1 (08:00 ET next business day if after hours) | F7: DS-92
A8: FINRA short interest | B8: 46387 | C8: 46392 | D8: 46399 | E8: M1 (08:00 ET next business day if after hours) | F8: DS-92
A9: FINRA short interest – rest of 2027 | B9: Pending | C9: Pending | D9: Mid-month and month-end settlements; FINRA publishes the next year's schedule late in the year – add when published | E9: M1 | F9: DS-92
A10: CPI, PCE, trade, FOMC | B10: — | C10: — | D10: Pulled automatically each morning by D1 from BLS schedule (DS-22) and FRED releases (DS-26) | E10: M1 | F10: DS-21, DS-24, DS-34
A11: Tesla deliveries | B11: Quarter end | C11: — | D11: ~2nd day after quarter end (UI plots on this release date) | E11: Q1 | F11: DS-12

Sheet Series IDs
A1: Provider | B1: Series / Code | C1: Description | D1: Frequency | E1: Category
A2: FRED | B2: DGS2 | C2: 2-Year Treasury yield | D2: Daily | E2: Bond yields
A3: FRED | B3: DGS10 | C3: 10-Year Treasury yield | D3: Daily | E3: Bond yields
A4: FRED | B4: DGS30 | C4: 30-Year Treasury yield | D4: Daily | E4: Bond yields
A5: FRED | B5: T10Y2Y | C5: 10Y minus 2Y spread | D5: Daily | E5: Bond yields
A6: FRED | B6: DFII10 | C6: 10-Year TIPS (real) yield | D6: Daily | E6: Bond yields
A7: FRED | B7: DFEDTARU | C7: Fed funds target – upper | D7: Daily | E7: Interest rates
A8: FRED | B8: DFEDTARL | C8: Fed funds target – lower | D8: Daily | E8: Interest rates
A9: FRED | B9: EFFR | C9: Effective fed funds rate | D9: Daily | E9: Interest rates
A10: FRED | B10: CPIAUCSL | C10: CPI-U all items, SA | D10: Monthly | E10: Inflation
A11: FRED | B11: CPILFESL | C11: Core CPI (ex food & energy), SA | D11: Monthly | E11: Inflation
A12: FRED | B12: PCEPI | C12: PCE price index | D12: Monthly | E12: Inflation
... A55: LL2 | B55: lsp__name=SpaceX | C55: Launch Library 2 provider filter | D55: Hourly | E55: SpaceX launches

Sheet Notes
A1: Investor Dashboard – Data Source Catalog
A2: Compiled 2026-10-03. Endpoints verified against public docs as of this date; free-tier limits change often — confirm before production use.
A3: Collection rule: nothing is polled more often than once an hour. Sources are sorted by cadence (Hourly → Daily → Weekly → Monthly/on release → Quarterly → Annual → One-time → Failover → Not used / merged), then by batch job and ID.
A4: Batching: each Batch Job runs all of its sources in one scheduled pass, so the scheduler wakes up 14 times a day rather than once per source. See the Batch Schedule tab for job times and call totals (formulas).
A5: Call-reduction rules applied: (1) multi-ticker / multi-term queries combined into one call where the API allows; (2) backups are polled only when the primary fails (Failover only = 0 calls normally); (3) duplicate sources merged (DS-49, DS-78, DS-79); (4) release data (CPI, PCE, trade) fetched once at release time, using dates pulled by job D1.
A6: Blue numbers (Calls / Run, Runs / Month) are editable assumptions; Calls / Month and the Batch Schedule totals recalculate. Runs / Month uses 251 NYSE trading days, 250 US federal business days and 249 bond-market days per year (2026 and 2027), divided by 12. Avg Calls / Day divides by 30 calendar days.
A7: No collection on weekends or holidays: every job follows the Holiday Calendar named on its row (see the Holiday Calendar tab). Regional sources (China MOFCOM/MIIT, Netherlands RDW) are also skipped on that country's holidays. Weekly jobs move to the next business day; feeds catch up on the first run after a gap, so nothing is lost.
A8: Times are US Eastern (source release times are published in ET); PT column = ET − 3 hours.
A9: {KEY} = your API key; {d} = date YYYY-MM-DD; {TICKER} = any tracked ticker.
A10: Ticker scope: collectors read the UNION of all users' tickers (default TSLA, SPCX + ETF proxies SPY, DIA, QQQ, IWM, XLY, ITA, SMH). Alpaca and Massive scale by adding symbols to the same calls; Alpha Vantage sentiment stays capped at 16 calls/day using a fixed list or rotation, so more tickers = less frequent sentiment per ticker.
A11: New ticker added by a user: run the DS-05 5-year daily backfill once for that ticker, then it joins the hourly (DS-02) and daily-close (DS-01) calls.
A12: SEC EDGAR requires a descriptive User-Agent header (name + email) and ≤10 requests/second.
... A15: $0 data budget: all sources use free tiers; paid upgrades declined are listed on the Cost Summary tab with their free replacements. Cost: see Cost Summary tab. Priority P1/P2/P3 and Likelihood of Paying are on each Data Sources row; expected monthly cost is probability-weighted.
